{
  "url": "https://www.tiktok.com/@shara.gym/video/7277616516865002784",
  "crawled_at": "2025-12-16T00:01:17.080087Z",
  "oembed": {
    "version": "1.0",
    "type": "video",
    "title": "Sexy secretary  #secretary #seductive #sexy #girl #body #viral #fyp #foryou ",
    "author_url": "https://www.tiktok.com/@shara.gym",
    "author_name": "shara",
    "width": "100%",
    "height": "100%",
    "html": "<blockquote class=\"tiktok-embed\" cite=\"https://www.tiktok.com/@shara.gym/video/7277616516865002784\" data-video-id=\"7277616516865002784\" data-embed-from=\"oembed\" style=\"max-width:605px; min-width:325px;\"> <section> <a target=\"_blank\" title=\"@shara.gym\" href=\"https://www.tiktok.com/@shara.gym?refer=embed\">@shara.gym</a> <p>Sexy secretary  <a title=\"secretary\" target=\"_blank\" href=\"https://www.tiktok.com/tag/secretary?refer=embed\">#secretary</a> <a title=\"seductive\" target=\"_blank\" href=\"https://www.tiktok.com/tag/seductive?refer=embed\">#seductive</a> <a title=\"sexy\" target=\"_blank\" href=\"https://www.tiktok.com/tag/sexy?refer=embed\">#sexy</a> <a title=\"girl\" target=\"_blank\" href=\"https://www.tiktok.com/tag/girl?refer=embed\">#girl</a> <a title=\"body\" target=\"_blank\" href=\"https://www.tiktok.com/tag/body?refer=embed\">#body</a> <a title=\"viral\" target=\"_blank\" href=\"https://www.tiktok.com/tag/viral?refer=embed\">#viral</a> <a title=\"fyp\" target=\"_blank\" href=\"https://www.tiktok.com/tag/fyp?refer=embed\">#fyp</a> <a title=\"foryou\" target=\"_blank\" href=\"https://www.tiktok.com/tag/foryou?refer=embed\">#foryou</a> </p> <a target=\"_blank\" title=\"♬ All Eyes On Me - Instrumental - Dj Belite\" href=\"https://www.tiktok.com/music/All-Eyes-On-Me-Instrumental-7182781797455890434?refer=embed\">♬ All Eyes On Me - Instrumental - Dj Belite</a> </section> </blockquote> <script async src=\"https://www.tiktok.com/embed.js\"></script>",
    "thumbnail_width": 576,
    "thumbnail_height": 1024,
    "thumbnail_url": "https://p19-common-sign-useastred.tiktokcdn-eu.com/tos-useast2a-p-0037-euttp/ocfYgfnCgQJIev2jJebEjsvEaI56S0IiADGSBI~tplv-tiktokx-origin.image?dr=14575&x-expires=1766016000&x-signature=cRxUpBJoUvpE6i2yEJGOJPqbf14%3D&t=4d5b0474&ps=13740610&shp=81f88b70&shcp=43f4a2f9&idc=my",
    "provider_url": "https://www.tiktok.com",
    "provider_name": "TikTok",
    "author_unique_id": "shara.gym",
    "embed_product_id": "7277616516865002784",
    "embed_type": "video"
  },
  "yt_dlp_info": {
    "id": "7277616516865002784",
    "formats": [
      {
        "ext": "mp4",
        "vcodec": "h264",
        "acodec": "aac",
        "format_id": "download",
        "url": "https://webapp-sg.tiktok.com/22047ae9712d44549028b260a9273887/69434457/kmoat/mps/logo/v2/r/p/v0f044gc0000cjvkhrrc77u4b325mskg/9b2d29272e474b949d29ce3b7614d610/441b42888e27b3264f40c33f0a6b723c/mp4/main.mp4?a=1988&bti=ODszNWYuMDE6&ch=0&cr=3&dr=0&lr=all&cd=0%7C0%7C0%7C&cv=1&br=0&bt=0&cs=0&ds=3&ft=bLZkAm7nPD12NHcSZd-Ux_TvXY6e3wv251cAp&mime_type=video_mp4&qs=0&rc=cnF8b2hsc2d3SkBwaHIxaDFybndmMzk3OWVoPGc3ZTpoOjxnZUBpanY4Njc6ZnVubTMzZjczM0BjRl5Nc3FePmJKYSNvYF90aHFmOiMuYS40MGAvNjYxMS8vLy82YSNoai9fcjRvZXNgLS1kMWNzcw%3D%3D&btag=e000b0000&definition=720p&du=11&item_id=7277616516865002784&l=202512160801176868EDCD479534677EBE&logo_type=tiktok_m&ply_type=2&policy=eyJ2bSI6MiwiY2siOiJ0dF9jaGFpbl90b2tlbiJ9&user_text=shara.gym",
        "format_note": "watermarked",
        "preference": -2,
        "protocol": "https",
        "video_ext": "mp4",
        "audio_ext": "none",
        "dynamic_range": "SDR",
        "cookies": "_ttp=34wyWDXvxmF602Htsl0oDR6JCNq; Domain=.tiktok.com; Path=/; Secure; Expires=1795834961; tt_csrf_token=A6kVUZcK-ro_L6C62WbmQwfALArHC4HF-pTM; Domain=.tiktok.com; Path=/; Secure; tt_chain_token=\"bIQCOyoJbQ000pox+IBxHQ==\"; Domain=.tiktok.com; Path=/; Secure; Expires=1781395277; passport_csrf_token=3e2175a5e77e24a26515b4e6f7b50740; Domain=.tiktok.com; Path=/; Secure; Expires=1767674732; passport_csrf_token_default=3e2175a5e77e24a26515b4e6f7b50740; Domain=.tiktok.com; Path=/; Secure; Expires=1767674732; s_v_web_id=verify_mhodh7s9_f6H7RhcI_zN3b_4VwP_AxSW_OnDGZUzFJBgu; Domain=.tiktok.com; Path=/; Secure; multi_sids=7569810985282094098%3Aade59ff71c0c0e5cc0fe1f23772b37c1; Domain=.tiktok.com; Path=/; Secure; Expires=1767677004; cmpl_token=AgQQAPOFF-RO0rkzsFuCpB0r82zGAoWNv4UOYKOhVw; Domain=.tiktok.com; Path=/; Secure; Expires=1767677004; sid_guard=ade59ff71c0c0e5cc0fe1f23772b37c1%7C1762493004%7C15552000%7CWed%2C+06-May-2026+05%3A23%3A24+GMT; Domain=.tiktok.com; Path=/; Secure; Expires=1793597004; uid_tt=ac0557b89a0248004ba199e09ced5e656aa70515a78deb5b62cd048a83d31edc; Domain=.tiktok.com; Path=/; Secure; Expires=1778045004; uid_tt_ss=ac0557b89a0248004ba199e09ced5e656aa70515a78deb5b62cd048a83d31edc; Domain=.tiktok.com; Path=/; Secure; Expires=1778045004; sid_tt=ade59ff71c0c0e5cc0fe1f23772b37c1; Domain=.tiktok.com; Path=/; Secure; Expires=1778045004; sessionid=ade59ff71c0c0e5cc0fe1f23772b37c1; Domain=.tiktok.com; Path=/; Secure; Expires=1778045004; sessionid_ss=ade59ff71c0c0e5cc0fe1f23772b37c1; Domain=.tiktok.com; Path=/; Secure; Expires=1778045004; tt_session_tlb_tag=sttt%7C5%7CreWf9xwMDlzA_h8jdys3wf________-ji4fpfjT0V1140MZnLSHWNBnXgRLIZvw1fxmxRRmvw7s%3D; Domain=.tiktok.com; Path=/; Secure; Expires=1778045004; sid_ucp_v1=1.0.0-KDYzMTBmY2U1ODFjN2FkYjNmOGUwYWE1YjcwYTk2N2FkYzhhMjMxMTEKIQiSiNvUwN_XhmkQzIS2yAYYswsgDDC1vrXIBjgIQBJIBBADGgJteSIgYWRlNTlmZjcxYzBjMGU1Y2MwZmUxZjIzNzcyYjM3YzE; Domain=.tiktok.com; Path=/; Secure; Expires=1778045004; ssid_ucp_v1=1.0.0-KDYzMTBmY2U1ODFjN2FkYjNmOGUwYWE1YjcwYTk2N2FkYzhhMjMxMTEKIQiSiNvUwN_XhmkQzIS2yAYYswsgDDC1vrXIBjgIQBJIBBADGgJteSIgYWRlNTlmZjcxYzBjMGU1Y2MwZmUxZjIzNzcyYjM3YzE; Domain=.tiktok.com; Path=/; Secure; Expires=1778045004; store-country-code=vn; Domain=.tiktok.com; Path=/; Expires=1794029034; store-country-code-src=uid; Domain=.tiktok.com; Path=/; Expires=1794029034; tt-target-idc=alisg; Domain=.tiktok.com; Path=/; Expires=1794029034; tt-target-idc-sign=X46gRkvSgmGWHXja-gzeN1KwdE4cBtH3zFXAhG3-BtWzH-YdFZEQct_uBwMTYtfjrNxqy_GJyyU9vrDSU9xBVMhZYzNMj8Yj-vL3ZdUiBlJfwT_RyqsMw9cBp-UMAurlaLw7iKPn1sOB_2Mr4OgfdC72r1rSon8aLN6RpZxfHlcPgzQDAzxGLO1WCcDi3Grn071JYzpIP3H4Uj5tKf5cHSGRn8O-z3hwE-QaTWdxP_Dv9m7mqKXg9LpTBaiRQ0apSWQMga4QK4y5B4To6e0pZD8oaixa2PVdqGeLesDSGOjsT94m5Qtsw2dBLvi1Cl2PDtg34s_m8F2kwZanwVGyMx5JeHbhEA1jVyuFTZ4wmF-6mQMCj4IoVYUBqf6cEHJl1nz6p3h7j4AFPdhgbDj7nwn0zI1o0xP8WGmE_kn9e53ehBx6IU-iOQJ-JXc_4e8_1n_tP7nZqBQAfB5B-a8mW0iUyH2XBzKKIebPZ8u02eRKDVUUZnutFcgBXjbQW4hW; Domain=.tiktok.com; Path=/; Expires=1794029034; ttwid=1%7CyHVVoWeMmc-3HMQzGeLAWTKsoEmn5lOxHLhrceV4g3w%7C1762493033%7Caa33d6157603beb187ae2fd554015cf463e69a9385fbc54d7a3e7a848a9df8fc; Domain=.tiktok.com; Path=/; Secure; Expires=1794029034; store-idc=alisg; Domain=.tiktok.com; Path=/; Expires=1794029034; store-country-sign=MEIEDGNAqWqR2a0er4zjeAQgMuurAVNuf3SOpc_lCsUS6OVOTEMJPGY7fje3VCShvuYEEKSUWUChT9xgz3oinfsoj_8; Domain=.tiktok.com; Path=/; Expires=1794029034; odin_tt=fdb338ea9924b66e069cd3826b52e91602d6c7c70440ed4a45253d1bdcb67e7b33079c363923c1afe01be7d6a0aed5f094b6d26ad61219129e2c4adf8ef71b17c80e515b61a158847d9b8a0bdf5ce20d; Domain=.tiktok.com; Path=/; Expires=1794029677; msToken=\"hx7BSPgRgPpecRzth56d-4VmoMwLX3y6d4CTS7XghO6T-s3uYyauu6s_q4fR0IXZe4yMTJWOmOjslVTkK-NEj_mMoww1_RiOAdVG_G6uzPyJMQiCzsXhIswbgY6slrxU-tenhjM2l9KyXpw=\"; Domain=.tiktok.com; Path=/; Secure; Expires=1766707277",
        "http_headers": {
          "User-Agent": "Mozilla/5.0",
          "Accept": "text/html,application/xhtml+xml,application/xml;q=0.9,*/*;q=0.8",
          "Accept-Language": "en-us,en;q=0.5",
          "Sec-Fetch-Mode": "navigate",
          "Referer": "https://www.tiktok.com/@shara.gym/video/7277616516865002784"
        },
        "format": "download - unknown (watermarked)"
      },
      {
        "ext": "mp4",
        "vcodec": "h264",
        "acodec": "aac",
        "format_id": "h264_540p_656189-0",
        "tbr": 656,
        "quality": 1,
        "preference": -1,
        "filesize": 883641,
        "width": 576,
        "height": 1024,
        "url": "https://v16-webapp-prime.tiktok.com/video/tos/useast2a/tos-useast2a-ve-0068c001-euttp/oA3iS0csnIPbSfIjA2eaeQjv5EbDJ9GQDXgYIf/?a=1988&bti=ODszNWYuMDE6&ch=0&cr=3&dr=0&lr=all&cd=0%7C0%7C0%7C&cv=1&br=1280&bt=640&cs=0&ds=6&ft=-Csk_m7nPD12NHcSZd-Ux_TvXY6e3wv251cAp&mime_type=video_mp4&qs=0&rc=ZzY8ODxnOGZmaTg1OzY4aEBpanY4Njc6ZnVubTMzZjczM0AwMTU1Mi1eXi8xYTUtXzZiYSNoai9fcjRvZXNgLS1kMWNzcw%3D%3D&btag=e000b0000&expire=1766016087&l=202512160801176868EDCD479534677EBE&ply_type=2&policy=2&signature=71c07d7d1e4237bc71073bb5a0fae08f&tk=tt_chain_token",
        "protocol": "https",
        "video_ext": "mp4",
        "audio_ext": "none",
        "resolution": "576x1024",
        "dynamic_range": "SDR",
        "aspect_ratio": 0.56,
        "cookies": "_ttp=34wyWDXvxmF602Htsl0oDR6JCNq; Domain=.tiktok.com; Path=/; Secure; Expires=1795834961; tt_csrf_token=A6kVUZcK-ro_L6C62WbmQwfALArHC4HF-pTM; Domain=.tiktok.com; Path=/; Secure; tt_chain_token=\"bIQCOyoJbQ000pox+IBxHQ==\"; Domain=.tiktok.com; Path=/; Secure; Expires=1781395277; passport_csrf_token=3e2175a5e77e24a26515b4e6f7b50740; Domain=.tiktok.com; Path=/; Secure; Expires=1767674732; passport_csrf_token_default=3e2175a5e77e24a26515b4e6f7b50740; Domain=.tiktok.com; Path=/; Secure; Expires=1767674732; s_v_web_id=verify_mhodh7s9_f6H7RhcI_zN3b_4VwP_AxSW_OnDGZUzFJBgu; Domain=.tiktok.com; Path=/; Secure; multi_sids=7569810985282094098%3Aade59ff71c0c0e5cc0fe1f23772b37c1; Domain=.tiktok.com; Path=/; Secure; Expires=1767677004; cmpl_token=AgQQAPOFF-RO0rkzsFuCpB0r82zGAoWNv4UOYKOhVw; Domain=.tiktok.com; Path=/; Secure; Expires=1767677004; sid_guard=ade59ff71c0c0e5cc0fe1f23772b37c1%7C1762493004%7C15552000%7CWed%2C+06-May-2026+05%3A23%3A24+GMT; Domain=.tiktok.com; Path=/; Secure; Expires=1793597004; uid_tt=ac0557b89a0248004ba199e09ced5e656aa70515a78deb5b62cd048a83d31edc; Domain=.tiktok.com; Path=/; Secure; Expires=1778045004; uid_tt_ss=ac0557b89a0248004ba199e09ced5e656aa70515a78deb5b62cd048a83d31edc; Domain=.tiktok.com; Path=/; Secure; Expires=1778045004; sid_tt=ade59ff71c0c0e5cc0fe1f23772b37c1; Domain=.tiktok.com; Path=/; Secure; Expires=1778045004; sessionid=ade59ff71c0c0e5cc0fe1f23772b37c1; Domain=.tiktok.com; Path=/; Secure; Expires=1778045004; sessionid_ss=ade59ff71c0c0e5cc0fe1f23772b37c1; Domain=.tiktok.com; Path=/; Secure; Expires=1778045004; tt_session_tlb_tag=sttt%7C5%7CreWf9xwMDlzA_h8jdys3wf________-ji4fpfjT0V1140MZnLSHWNBnXgRLIZvw1fxmxRRmvw7s%3D; Domain=.tiktok.com; Path=/; Secure; Expires=1778045004; sid_ucp_v1=1.0.0-KDYzMTBmY2U1ODFjN2FkYjNmOGUwYWE1YjcwYTk2N2FkYzhhMjMxMTEKIQiSiNvUwN_XhmkQzIS2yAYYswsgDDC1vrXIBjgIQBJIBBADGgJteSIgYWRlNTlmZjcxYzBjMGU1Y2MwZmUxZjIzNzcyYjM3YzE; Domain=.tiktok.com; Path=/; Secure; Expires=1778045004; ssid_ucp_v1=1.0.0-KDYzMTBmY2U1ODFjN2FkYjNmOGUwYWE1YjcwYTk2N2FkYzhhMjMxMTEKIQiSiNvUwN_XhmkQzIS2yAYYswsgDDC1vrXIBjgIQBJIBBADGgJteSIgYWRlNTlmZjcxYzBjMGU1Y2MwZmUxZjIzNzcyYjM3YzE; Domain=.tiktok.com; Path=/; Secure; Expires=1778045004; store-country-code=vn; Domain=.tiktok.com; Path=/; Expires=1794029034; store-country-code-src=uid; Domain=.tiktok.com; Path=/; Expires=1794029034; tt-target-idc=alisg; Domain=.tiktok.com; Path=/; Expires=1794029034; tt-target-idc-sign=X46gRkvSgmGWHXja-gzeN1KwdE4cBtH3zFXAhG3-BtWzH-YdFZEQct_uBwMTYtfjrNxqy_GJyyU9vrDSU9xBVMhZYzNMj8Yj-vL3ZdUiBlJfwT_RyqsMw9cBp-UMAurlaLw7iKPn1sOB_2Mr4OgfdC72r1rSon8aLN6RpZxfHlcPgzQDAzxGLO1WCcDi3Grn071JYzpIP3H4Uj5tKf5cHSGRn8O-z3hwE-QaTWdxP_Dv9m7mqKXg9LpTBaiRQ0apSWQMga4QK4y5B4To6e0pZD8oaixa2PVdqGeLesDSGOjsT94m5Qtsw2dBLvi1Cl2PDtg34s_m8F2kwZanwVGyMx5JeHbhEA1jVyuFTZ4wmF-6mQMCj4IoVYUBqf6cEHJl1nz6p3h7j4AFPdhgbDj7nwn0zI1o0xP8WGmE_kn9e53ehBx6IU-iOQJ-JXc_4e8_1n_tP7nZqBQAfB5B-a8mW0iUyH2XBzKKIebPZ8u02eRKDVUUZnutFcgBXjbQW4hW; Domain=.tiktok.com; Path=/; Expires=1794029034; ttwid=1%7CyHVVoWeMmc-3HMQzGeLAWTKsoEmn5lOxHLhrceV4g3w%7C1762493033%7Caa33d6157603beb187ae2fd554015cf463e69a9385fbc54d7a3e7a848a9df8fc; Domain=.tiktok.com; Path=/; Secure; Expires=1794029034; store-idc=alisg; Domain=.tiktok.com; Path=/; Expires=1794029034; store-country-sign=MEIEDGNAqWqR2a0er4zjeAQgMuurAVNuf3SOpc_lCsUS6OVOTEMJPGY7fje3VCShvuYEEKSUWUChT9xgz3oinfsoj_8; Domain=.tiktok.com; Path=/; Expires=1794029034; odin_tt=fdb338ea9924b66e069cd3826b52e91602d6c7c70440ed4a45253d1bdcb67e7b33079c363923c1afe01be7d6a0aed5f094b6d26ad61219129e2c4adf8ef71b17c80e515b61a158847d9b8a0bdf5ce20d; Domain=.tiktok.com; Path=/; Expires=1794029677; msToken=\"hx7BSPgRgPpecRzth56d-4VmoMwLX3y6d4CTS7XghO6T-s3uYyauu6s_q4fR0IXZe4yMTJWOmOjslVTkK-NEj_mMoww1_RiOAdVG_G6uzPyJMQiCzsXhIswbgY6slrxU-tenhjM2l9KyXpw=\"; Domain=.tiktok.com; Path=/; Secure; Expires=1766707277",
        "http_headers": {
          "User-Agent": "Mozilla/5.0",
          "Accept": "text/html,application/xhtml+xml,application/xml;q=0.9,*/*;q=0.8",
          "Accept-Language": "en-us,en;q=0.5",
          "Sec-Fetch-Mode": "navigate",
          "Referer": "https://www.tiktok.com/@shara.gym/video/7277616516865002784"
        },
        "format": "h264_540p_656189-0 - 576x1024"
      },
      {
        "ext": "mp4",
        "vcodec": "h264",
        "acodec": "aac",
        "format_id": "h264_540p_656189-1",
        "tbr": 656,
        "quality": 1,
        "preference": -1,
        "filesize": 883641,
        "width": 576,
        "height": 1024,
        "url": "https://v19-webapp-prime.tiktok.com/video/tos/useast2a/tos-useast2a-ve-0068c001-euttp/oA3iS0csnIPbSfIjA2eaeQjv5EbDJ9GQDXgYIf/?a=1988&bti=ODszNWYuMDE6&ch=0&cr=3&dr=0&lr=all&cd=0%7C0%7C0%7C&cv=1&br=1280&bt=640&cs=0&ds=6&ft=-Csk_m7nPD12NHcSZd-Ux_TvXY6e3wv251cAp&mime_type=video_mp4&qs=0&rc=ZzY8ODxnOGZmaTg1OzY4aEBpanY4Njc6ZnVubTMzZjczM0AwMTU1Mi1eXi8xYTUtXzZiYSNoai9fcjRvZXNgLS1kMWNzcw%3D%3D&btag=e000b0000&expire=1766016087&l=202512160801176868EDCD479534677EBE&ply_type=2&policy=2&signature=71c07d7d1e4237bc71073bb5a0fae08f&tk=tt_chain_token",
        "protocol": "https",
        "video_ext": "mp4",
        "audio_ext": "none",
        "resolution": "576x1024",
        "dynamic_range": "SDR",
        "aspect_ratio": 0.56,
        "cookies": "_ttp=34wyWDXvxmF602Htsl0oDR6JCNq; Domain=.tiktok.com; Path=/; Secure; Expires=1795834961; tt_csrf_token=A6kVUZcK-ro_L6C62WbmQwfALArHC4HF-pTM; Domain=.tiktok.com; Path=/; Secure; tt_chain_token=\"bIQCOyoJbQ000pox+IBxHQ==\"; Domain=.tiktok.com; Path=/; Secure; Expires=1781395277; passport_csrf_token=3e2175a5e77e24a26515b4e6f7b50740; Domain=.tiktok.com; Path=/; Secure; Expires=1767674732; passport_csrf_token_default=3e2175a5e77e24a26515b4e6f7b50740; Domain=.tiktok.com; Path=/; Secure; Expires=1767674732; s_v_web_id=verify_mhodh7s9_f6H7RhcI_zN3b_4VwP_AxSW_OnDGZUzFJBgu; Domain=.tiktok.com; Path=/; Secure; multi_sids=7569810985282094098%3Aade59ff71c0c0e5cc0fe1f23772b37c1; Domain=.tiktok.com; Path=/; Secure; Expires=1767677004; cmpl_token=AgQQAPOFF-RO0rkzsFuCpB0r82zGAoWNv4UOYKOhVw; Domain=.tiktok.com; Path=/; Secure; Expires=1767677004; sid_guard=ade59ff71c0c0e5cc0fe1f23772b37c1%7C1762493004%7C15552000%7CWed%2C+06-May-2026+05%3A23%3A24+GMT; Domain=.tiktok.com; Path=/; Secure; Expires=1793597004; uid_tt=ac0557b89a0248004ba199e09ced5e656aa70515a78deb5b62cd048a83d31edc; Domain=.tiktok.com; Path=/; Secure; Expires=1778045004; uid_tt_ss=ac0557b89a0248004ba199e09ced5e656aa70515a78deb5b62cd048a83d31edc; Domain=.tiktok.com; Path=/; Secure; Expires=1778045004; sid_tt=ade59ff71c0c0e5cc0fe1f23772b37c1; Domain=.tiktok.com; Path=/; Secure; Expires=1778045004; sessionid=ade59ff71c0c0e5cc0fe1f23772b37c1; Domain=.tiktok.com; Path=/; Secure; Expires=1778045004; sessionid_ss=ade59ff71c0c0e5cc0fe1f23772b37c1; Domain=.tiktok.com; Path=/; Secure; Expires=1778045004; tt_session_tlb_tag=sttt%7C5%7CreWf9xwMDlzA_h8jdys3wf________-ji4fpfjT0V1140MZnLSHWNBnXgRLIZvw1fxmxRRmvw7s%3D; Domain=.tiktok.com; Path=/; Secure; Expires=1778045004; sid_ucp_v1=1.0.0-KDYzMTBmY2U1ODFjN2FkYjNmOGUwYWE1YjcwYTk2N2FkYzhhMjMxMTEKIQiSiNvUwN_XhmkQzIS2yAYYswsgDDC1vrXIBjgIQBJIBBADGgJteSIgYWRlNTlmZjcxYzBjMGU1Y2MwZmUxZjIzNzcyYjM3YzE; Domain=.tiktok.com; Path=/; Secure; Expires=1778045004; ssid_ucp_v1=1.0.0-KDYzMTBmY2U1ODFjN2FkYjNmOGUwYWE1YjcwYTk2N2FkYzhhMjMxMTEKIQiSiNvUwN_XhmkQzIS2yAYYswsgDDC1vrXIBjgIQBJIBBADGgJteSIgYWRlNTlmZjcxYzBjMGU1Y2MwZmUxZjIzNzcyYjM3YzE; Domain=.tiktok.com; Path=/; Secure; Expires=1778045004; store-country-code=vn; Domain=.tiktok.com; Path=/; Expires=1794029034; store-country-code-src=uid; Domain=.tiktok.com; Path=/; Expires=1794029034; tt-target-idc=alisg; Domain=.tiktok.com; Path=/; Expires=1794029034; tt-target-idc-sign=X46gRkvSgmGWHXja-gzeN1KwdE4cBtH3zFXAhG3-BtWzH-YdFZEQct_uBwMTYtfjrNxqy_GJyyU9vrDSU9xBVMhZYzNMj8Yj-vL3ZdUiBlJfwT_RyqsMw9cBp-UMAurlaLw7iKPn1sOB_2Mr4OgfdC72r1rSon8aLN6RpZxfHlcPgzQDAzxGLO1WCcDi3Grn071JYzpIP3H4Uj5tKf5cHSGRn8O-z3hwE-QaTWdxP_Dv9m7mqKXg9LpTBaiRQ0apSWQMga4QK4y5B4To6e0pZD8oaixa2PVdqGeLesDSGOjsT94m5Qtsw2dBLvi1Cl2PDtg34s_m8F2kwZanwVGyMx5JeHbhEA1jVyuFTZ4wmF-6mQMCj4IoVYUBqf6cEHJl1nz6p3h7j4AFPdhgbDj7nwn0zI1o0xP8WGmE_kn9e53ehBx6IU-iOQJ-JXc_4e8_1n_tP7nZqBQAfB5B-a8mW0iUyH2XBzKKIebPZ8u02eRKDVUUZnutFcgBXjbQW4hW; Domain=.tiktok.com; Path=/; Expires=1794029034; ttwid=1%7CyHVVoWeMmc-3HMQzGeLAWTKsoEmn5lOxHLhrceV4g3w%7C1762493033%7Caa33d6157603beb187ae2fd554015cf463e69a9385fbc54d7a3e7a848a9df8fc; Domain=.tiktok.com; Path=/; Secure; Expires=1794029034; store-idc=alisg; Domain=.tiktok.com; Path=/; Expires=1794029034; store-country-sign=MEIEDGNAqWqR2a0er4zjeAQgMuurAVNuf3SOpc_lCsUS6OVOTEMJPGY7fje3VCShvuYEEKSUWUChT9xgz3oinfsoj_8; Domain=.tiktok.com; Path=/; Expires=1794029034; odin_tt=fdb338ea9924b66e069cd3826b52e91602d6c7c70440ed4a45253d1bdcb67e7b33079c363923c1afe01be7d6a0aed5f094b6d26ad61219129e2c4adf8ef71b17c80e515b61a158847d9b8a0bdf5ce20d; Domain=.tiktok.com; Path=/; Expires=1794029677; msToken=\"hx7BSPgRgPpecRzth56d-4VmoMwLX3y6d4CTS7XghO6T-s3uYyauu6s_q4fR0IXZe4yMTJWOmOjslVTkK-NEj_mMoww1_RiOAdVG_G6uzPyJMQiCzsXhIswbgY6slrxU-tenhjM2l9KyXpw=\"; Domain=.tiktok.com; Path=/; Secure; Expires=1766707277",
        "http_headers": {
          "User-Agent": "Mozilla/5.0",
          "Accept": "text/html,application/xhtml+xml,application/xml;q=0.9,*/*;q=0.8",
          "Accept-Language": "en-us,en;q=0.5",
          "Sec-Fetch-Mode": "navigate",
          "Referer": "https://www.tiktok.com/@shara.gym/video/7277616516865002784"
        },
        "format": "h264_540p_656189-1 - 576x1024"
      },
      {
        "ext": "mp4",
        "vcodec": "h265",
        "acodec": "aac",
        "format_id": "bytevc1_540p_378533-0",
        "tbr": 378,
        "quality": 1,
        "preference": -1,
        "filesize": 509743,
        "width": 576,
        "height": 1024,
        "url": "https://v16-webapp-prime.tiktok.com/video/tos/useast2a/tos-useast2a-ve-0068-euttp/oMcOBwyYkeKBWkEZ7JePjexdSXIfEfA0B3Fe9T/?a=1988&bti=ODszNWYuMDE6&ch=0&cr=3&dr=0&lr=all&cd=0%7C0%7C0%7C&cv=1&br=738&bt=369&cs=2&ds=6&ft=-Csk_m7nPD12NHcSZd-Ux_TvXY6e3wv251cAp&mime_type=video_mp4&qs=11&rc=OmZoMzM3ZzRmZztnO2g7aUBpanY4Njc6ZnVubTMzZjczM0BeMmNiYV82NV8xYS9gNV8xYSNoai9fcjRvZXNgLS1kMWNzcw%3D%3D&btag=e000b0000&expire=1766016087&l=202512160801176868EDCD479534677EBE&ply_type=2&policy=2&signature=22cb7144c8dbf580c66a6d86b9cb88d1&tk=tt_chain_token",
        "protocol": "https",
        "video_ext": "mp4",
        "audio_ext": "none",
        "resolution": "576x1024",
        "dynamic_range": "SDR",
        "aspect_ratio": 0.56,
        "cookies": "_ttp=34wyWDXvxmF602Htsl0oDR6JCNq; Domain=.tiktok.com; Path=/; Secure; Expires=1795834961; tt_csrf_token=A6kVUZcK-ro_L6C62WbmQwfALArHC4HF-pTM; Domain=.tiktok.com; Path=/; Secure; tt_chain_token=\"bIQCOyoJbQ000pox+IBxHQ==\"; Domain=.tiktok.com; Path=/; Secure; Expires=1781395277; passport_csrf_token=3e2175a5e77e24a26515b4e6f7b50740; Domain=.tiktok.com; Path=/; Secure; Expires=1767674732; passport_csrf_token_default=3e2175a5e77e24a26515b4e6f7b50740; Domain=.tiktok.com; Path=/; Secure; Expires=1767674732; s_v_web_id=verify_mhodh7s9_f6H7RhcI_zN3b_4VwP_AxSW_OnDGZUzFJBgu; Domain=.tiktok.com; Path=/; Secure; multi_sids=7569810985282094098%3Aade59ff71c0c0e5cc0fe1f23772b37c1; Domain=.tiktok.com; Path=/; Secure; Expires=1767677004; cmpl_token=AgQQAPOFF-RO0rkzsFuCpB0r82zGAoWNv4UOYKOhVw; Domain=.tiktok.com; Path=/; Secure; Expires=1767677004; sid_guard=ade59ff71c0c0e5cc0fe1f23772b37c1%7C1762493004%7C15552000%7CWed%2C+06-May-2026+05%3A23%3A24+GMT; Domain=.tiktok.com; Path=/; Secure; Expires=1793597004; uid_tt=ac0557b89a0248004ba199e09ced5e656aa70515a78deb5b62cd048a83d31edc; Domain=.tiktok.com; Path=/; Secure; Expires=1778045004; uid_tt_ss=ac0557b89a0248004ba199e09ced5e656aa70515a78deb5b62cd048a83d31edc; Domain=.tiktok.com; Path=/; Secure; Expires=1778045004; sid_tt=ade59ff71c0c0e5cc0fe1f23772b37c1; Domain=.tiktok.com; Path=/; Secure; Expires=1778045004; sessionid=ade59ff71c0c0e5cc0fe1f23772b37c1; Domain=.tiktok.com; Path=/; Secure; Expires=1778045004; sessionid_ss=ade59ff71c0c0e5cc0fe1f23772b37c1; Domain=.tiktok.com; Path=/; Secure; Expires=1778045004; tt_session_tlb_tag=sttt%7C5%7CreWf9xwMDlzA_h8jdys3wf________-ji4fpfjT0V1140MZnLSHWNBnXgRLIZvw1fxmxRRmvw7s%3D; Domain=.tiktok.com; Path=/; Secure; Expires=1778045004; sid_ucp_v1=1.0.0-KDYzMTBmY2U1ODFjN2FkYjNmOGUwYWE1YjcwYTk2N2FkYzhhMjMxMTEKIQiSiNvUwN_XhmkQzIS2yAYYswsgDDC1vrXIBjgIQBJIBBADGgJteSIgYWRlNTlmZjcxYzBjMGU1Y2MwZmUxZjIzNzcyYjM3YzE; Domain=.tiktok.com; Path=/; Secure; Expires=1778045004; ssid_ucp_v1=1.0.0-KDYzMTBmY2U1ODFjN2FkYjNmOGUwYWE1YjcwYTk2N2FkYzhhMjMxMTEKIQiSiNvUwN_XhmkQzIS2yAYYswsgDDC1vrXIBjgIQBJIBBADGgJteSIgYWRlNTlmZjcxYzBjMGU1Y2MwZmUxZjIzNzcyYjM3YzE; Domain=.tiktok.com; Path=/; Secure; Expires=1778045004; store-country-code=vn; Domain=.tiktok.com; Path=/; Expires=1794029034; store-country-code-src=uid; Domain=.tiktok.com; Path=/; Expires=1794029034; tt-target-idc=alisg; Domain=.tiktok.com; Path=/; Expires=1794029034; tt-target-idc-sign=X46gRkvSgmGWHXja-gzeN1KwdE4cBtH3zFXAhG3-BtWzH-YdFZEQct_uBwMTYtfjrNxqy_GJyyU9vrDSU9xBVMhZYzNMj8Yj-vL3ZdUiBlJfwT_RyqsMw9cBp-UMAurlaLw7iKPn1sOB_2Mr4OgfdC72r1rSon8aLN6RpZxfHlcPgzQDAzxGLO1WCcDi3Grn071JYzpIP3H4Uj5tKf5cHSGRn8O-z3hwE-QaTWdxP_Dv9m7mqKXg9LpTBaiRQ0apSWQMga4QK4y5B4To6e0pZD8oaixa2PVdqGeLesDSGOjsT94m5Qtsw2dBLvi1Cl2PDtg34s_m8F2kwZanwVGyMx5JeHbhEA1jVyuFTZ4wmF-6mQMCj4IoVYUBqf6cEHJl1nz6p3h7j4AFPdhgbDj7nwn0zI1o0xP8WGmE_kn9e53ehBx6IU-iOQJ-JXc_4e8_1n_tP7nZqBQAfB5B-a8mW0iUyH2XBzKKIebPZ8u02eRKDVUUZnutFcgBXjbQW4hW; Domain=.tiktok.com; Path=/; Expires=1794029034; ttwid=1%7CyHVVoWeMmc-3HMQzGeLAWTKsoEmn5lOxHLhrceV4g3w%7C1762493033%7Caa33d6157603beb187ae2fd554015cf463e69a9385fbc54d7a3e7a848a9df8fc; Domain=.tiktok.com; Path=/; Secure; Expires=1794029034; store-idc=alisg; Domain=.tiktok.com; Path=/; Expires=1794029034; store-country-sign=MEIEDGNAqWqR2a0er4zjeAQgMuurAVNuf3SOpc_lCsUS6OVOTEMJPGY7fje3VCShvuYEEKSUWUChT9xgz3oinfsoj_8; Domain=.tiktok.com; Path=/; Expires=1794029034; odin_tt=fdb338ea9924b66e069cd3826b52e91602d6c7c70440ed4a45253d1bdcb67e7b33079c363923c1afe01be7d6a0aed5f094b6d26ad61219129e2c4adf8ef71b17c80e515b61a158847d9b8a0bdf5ce20d; Domain=.tiktok.com; Path=/; Expires=1794029677; msToken=\"hx7BSPgRgPpecRzth56d-4VmoMwLX3y6d4CTS7XghO6T-s3uYyauu6s_q4fR0IXZe4yMTJWOmOjslVTkK-NEj_mMoww1_RiOAdVG_G6uzPyJMQiCzsXhIswbgY6slrxU-tenhjM2l9KyXpw=\"; Domain=.tiktok.com; Path=/; Secure; Expires=1766707277",
        "http_headers": {
          "User-Agent": "Mozilla/5.0",
          "Accept": "text/html,application/xhtml+xml,application/xml;q=0.9,*/*;q=0.8",
          "Accept-Language": "en-us,en;q=0.5",
          "Sec-Fetch-Mode": "navigate",
          "Referer": "https://www.tiktok.com/@shara.gym/video/7277616516865002784"
        },
        "format": "bytevc1_540p_378533-0 - 576x1024"
      },
      {
        "ext": "mp4",
        "vcodec": "h265",
        "acodec": "aac",
        "format_id": "bytevc1_540p_378533-1",
        "tbr": 378,
        "quality": 1,
        "preference": -1,
        "filesize": 509743,
        "width": 576,
        "height": 1024,
        "url": "https://v19-webapp-prime.tiktok.com/video/tos/useast2a/tos-useast2a-ve-0068-euttp/oMcOBwyYkeKBWkEZ7JePjexdSXIfEfA0B3Fe9T/?a=1988&bti=ODszNWYuMDE6&ch=0&cr=3&dr=0&lr=all&cd=0%7C0%7C0%7C&cv=1&br=738&bt=369&cs=2&ds=6&ft=-Csk_m7nPD12NHcSZd-Ux_TvXY6e3wv251cAp&mime_type=video_mp4&qs=11&rc=OmZoMzM3ZzRmZztnO2g7aUBpanY4Njc6ZnVubTMzZjczM0BeMmNiYV82NV8xYS9gNV8xYSNoai9fcjRvZXNgLS1kMWNzcw%3D%3D&btag=e000b0000&expire=1766016087&l=202512160801176868EDCD479534677EBE&ply_type=2&policy=2&signature=22cb7144c8dbf580c66a6d86b9cb88d1&tk=tt_chain_token",
        "protocol": "https",
        "video_ext": "mp4",
        "audio_ext": "none",
        "resolution": "576x1024",
        "dynamic_range": "SDR",
        "aspect_ratio": 0.56,
        "cookies": "_ttp=34wyWDXvxmF602Htsl0oDR6JCNq; Domain=.tiktok.com; Path=/; Secure; Expires=1795834961; tt_csrf_token=A6kVUZcK-ro_L6C62WbmQwfALArHC4HF-pTM; Domain=.tiktok.com; Path=/; Secure; tt_chain_token=\"bIQCOyoJbQ000pox+IBxHQ==\"; Domain=.tiktok.com; Path=/; Secure; Expires=1781395277; passport_csrf_token=3e2175a5e77e24a26515b4e6f7b50740; Domain=.tiktok.com; Path=/; Secure; Expires=1767674732; passport_csrf_token_default=3e2175a5e77e24a26515b4e6f7b50740; Domain=.tiktok.com; Path=/; Secure; Expires=1767674732; s_v_web_id=verify_mhodh7s9_f6H7RhcI_zN3b_4VwP_AxSW_OnDGZUzFJBgu; Domain=.tiktok.com; Path=/; Secure; multi_sids=7569810985282094098%3Aade59ff71c0c0e5cc0fe1f23772b37c1; Domain=.tiktok.com; Path=/; Secure; Expires=1767677004; cmpl_token=AgQQAPOFF-RO0rkzsFuCpB0r82zGAoWNv4UOYKOhVw; Domain=.tiktok.com; Path=/; Secure; Expires=1767677004; sid_guard=ade59ff71c0c0e5cc0fe1f23772b37c1%7C1762493004%7C15552000%7CWed%2C+06-May-2026+05%3A23%3A24+GMT; Domain=.tiktok.com; Path=/; Secure; Expires=1793597004; uid_tt=ac0557b89a0248004ba199e09ced5e656aa70515a78deb5b62cd048a83d31edc; Domain=.tiktok.com; Path=/; Secure; Expires=1778045004; uid_tt_ss=ac0557b89a0248004ba199e09ced5e656aa70515a78deb5b62cd048a83d31edc; Domain=.tiktok.com; Path=/; Secure; Expires=1778045004; sid_tt=ade59ff71c0c0e5cc0fe1f23772b37c1; Domain=.tiktok.com; Path=/; Secure; Expires=1778045004; sessionid=ade59ff71c0c0e5cc0fe1f23772b37c1; Domain=.tiktok.com; Path=/; Secure; Expires=1778045004; sessionid_ss=ade59ff71c0c0e5cc0fe1f23772b37c1; Domain=.tiktok.com; Path=/; Secure; Expires=1778045004; tt_session_tlb_tag=sttt%7C5%7CreWf9xwMDlzA_h8jdys3wf________-ji4fpfjT0V1140MZnLSHWNBnXgRLIZvw1fxmxRRmvw7s%3D; Domain=.tiktok.com; Path=/; Secure; Expires=1778045004; sid_ucp_v1=1.0.0-KDYzMTBmY2U1ODFjN2FkYjNmOGUwYWE1YjcwYTk2N2FkYzhhMjMxMTEKIQiSiNvUwN_XhmkQzIS2yAYYswsgDDC1vrXIBjgIQBJIBBADGgJteSIgYWRlNTlmZjcxYzBjMGU1Y2MwZmUxZjIzNzcyYjM3YzE; Domain=.tiktok.com; Path=/; Secure; Expires=1778045004; ssid_ucp_v1=1.0.0-KDYzMTBmY2U1ODFjN2FkYjNmOGUwYWE1YjcwYTk2N2FkYzhhMjMxMTEKIQiSiNvUwN_XhmkQzIS2yAYYswsgDDC1vrXIBjgIQBJIBBADGgJteSIgYWRlNTlmZjcxYzBjMGU1Y2MwZmUxZjIzNzcyYjM3YzE; Domain=.tiktok.com; Path=/; Secure; Expires=1778045004; store-country-code=vn; Domain=.tiktok.com; Path=/; Expires=1794029034; store-country-code-src=uid; Domain=.tiktok.com; Path=/; Expires=1794029034; tt-target-idc=alisg; Domain=.tiktok.com; Path=/; Expires=1794029034; tt-target-idc-sign=X46gRkvSgmGWHXja-gzeN1KwdE4cBtH3zFXAhG3-BtWzH-YdFZEQct_uBwMTYtfjrNxqy_GJyyU9vrDSU9xBVMhZYzNMj8Yj-vL3ZdUiBlJfwT_RyqsMw9cBp-UMAurlaLw7iKPn1sOB_2Mr4OgfdC72r1rSon8aLN6RpZxfHlcPgzQDAzxGLO1WCcDi3Grn071JYzpIP3H4Uj5tKf5cHSGRn8O-z3hwE-QaTWdxP_Dv9m7mqKXg9LpTBaiRQ0apSWQMga4QK4y5B4To6e0pZD8oaixa2PVdqGeLesDSGOjsT94m5Qtsw2dBLvi1Cl2PDtg34s_m8F2kwZanwVGyMx5JeHbhEA1jVyuFTZ4wmF-6mQMCj4IoVYUBqf6cEHJl1nz6p3h7j4AFPdhgbDj7nwn0zI1o0xP8WGmE_kn9e53ehBx6IU-iOQJ-JXc_4e8_1n_tP7nZqBQAfB5B-a8mW0iUyH2XBzKKIebPZ8u02eRKDVUUZnutFcgBXjbQW4hW; Domain=.tiktok.com; Path=/; Expires=1794029034; ttwid=1%7CyHVVoWeMmc-3HMQzGeLAWTKsoEmn5lOxHLhrceV4g3w%7C1762493033%7Caa33d6157603beb187ae2fd554015cf463e69a9385fbc54d7a3e7a848a9df8fc; Domain=.tiktok.com; Path=/; Secure; Expires=1794029034; store-idc=alisg; Domain=.tiktok.com; Path=/; Expires=1794029034; store-country-sign=MEIEDGNAqWqR2a0er4zjeAQgMuurAVNuf3SOpc_lCsUS6OVOTEMJPGY7fje3VCShvuYEEKSUWUChT9xgz3oinfsoj_8; Domain=.tiktok.com; Path=/; Expires=1794029034; odin_tt=fdb338ea9924b66e069cd3826b52e91602d6c7c70440ed4a45253d1bdcb67e7b33079c363923c1afe01be7d6a0aed5f094b6d26ad61219129e2c4adf8ef71b17c80e515b61a158847d9b8a0bdf5ce20d; Domain=.tiktok.com; Path=/; Expires=1794029677; msToken=\"hx7BSPgRgPpecRzth56d-4VmoMwLX3y6d4CTS7XghO6T-s3uYyauu6s_q4fR0IXZe4yMTJWOmOjslVTkK-NEj_mMoww1_RiOAdVG_G6uzPyJMQiCzsXhIswbgY6slrxU-tenhjM2l9KyXpw=\"; Domain=.tiktok.com; Path=/; Secure; Expires=1766707277",
        "http_headers": {
          "User-Agent": "Mozilla/5.0",
          "Accept": "text/html,application/xhtml+xml,application/xml;q=0.9,*/*;q=0.8",
          "Accept-Language": "en-us,en;q=0.5",
          "Sec-Fetch-Mode": "navigate",
          "Referer": "https://www.tiktok.com/@shara.gym/video/7277616516865002784"
        },
        "format": "bytevc1_540p_378533-1 - 576x1024"
      },
      {
        "ext": "mp4",
        "vcodec": "h265",
        "acodec": "aac",
        "format_id": "bytevc1_720p_428555-0",
        "tbr": 428,
        "quality": 2,
        "preference": -1,
        "filesize": 577103,
        "width": 720,
        "height": 1280,
        "url": "https://v16-webapp-prime.tiktok.com/video/tos/useast2a/tos-useast2a-ve-0068c001-euttp/okRiaL2P4AiIMbnixaaJfflSfJ4AeHOn4GcehA/?a=1988&bti=ODszNWYuMDE6&ch=0&cr=3&dr=0&lr=all&cd=0%7C0%7C0%7C&cv=1&br=836&bt=418&cs=2&ds=3&ft=-Csk_m7nPD12NHcSZd-Ux_TvXY6e3wv251cAp&mime_type=video_mp4&qs=14&rc=cnF8b2hsc2d3SkBwaHIxaDFybndmN2lnOjg5ZWk6NzhkPDQ2OUBpanY4Njc6ZnVubTMzZjczM0BjRl5Nc3FePmJKYSNvYF90aHFmOiM1NGJgYGE0NmExMTZeXi5iYSNoai9fcjRvZXNgLS1kMWNzcw%3D%3D&btag=e000b0000&expire=1766016087&l=202512160801176868EDCD479534677EBE&ply_type=2&policy=2&signature=8f29aabc8d9bcf07c33254fd3ae44588&tk=tt_chain_token",
        "protocol": "https",
        "video_ext": "mp4",
        "audio_ext": "none",
        "resolution": "720x1280",
        "dynamic_range": "SDR",
        "aspect_ratio": 0.56,
        "cookies": "_ttp=34wyWDXvxmF602Htsl0oDR6JCNq; Domain=.tiktok.com; Path=/; Secure; Expires=1795834961; tt_csrf_token=A6kVUZcK-ro_L6C62WbmQwfALArHC4HF-pTM; Domain=.tiktok.com; Path=/; Secure; tt_chain_token=\"bIQCOyoJbQ000pox+IBxHQ==\"; Domain=.tiktok.com; Path=/; Secure; Expires=1781395277; passport_csrf_token=3e2175a5e77e24a26515b4e6f7b50740; Domain=.tiktok.com; Path=/; Secure; Expires=1767674732; passport_csrf_token_default=3e2175a5e77e24a26515b4e6f7b50740; Domain=.tiktok.com; Path=/; Secure; Expires=1767674732; s_v_web_id=verify_mhodh7s9_f6H7RhcI_zN3b_4VwP_AxSW_OnDGZUzFJBgu; Domain=.tiktok.com; Path=/; Secure; multi_sids=7569810985282094098%3Aade59ff71c0c0e5cc0fe1f23772b37c1; Domain=.tiktok.com; Path=/; Secure; Expires=1767677004; cmpl_token=AgQQAPOFF-RO0rkzsFuCpB0r82zGAoWNv4UOYKOhVw; Domain=.tiktok.com; Path=/; Secure; Expires=1767677004; sid_guard=ade59ff71c0c0e5cc0fe1f23772b37c1%7C1762493004%7C15552000%7CWed%2C+06-May-2026+05%3A23%3A24+GMT; Domain=.tiktok.com; Path=/; Secure; Expires=1793597004; uid_tt=ac0557b89a0248004ba199e09ced5e656aa70515a78deb5b62cd048a83d31edc; Domain=.tiktok.com; Path=/; Secure; Expires=1778045004; uid_tt_ss=ac0557b89a0248004ba199e09ced5e656aa70515a78deb5b62cd048a83d31edc; Domain=.tiktok.com; Path=/; Secure; Expires=1778045004; sid_tt=ade59ff71c0c0e5cc0fe1f23772b37c1; Domain=.tiktok.com; Path=/; Secure; Expires=1778045004; sessionid=ade59ff71c0c0e5cc0fe1f23772b37c1; Domain=.tiktok.com; Path=/; Secure; Expires=1778045004; sessionid_ss=ade59ff71c0c0e5cc0fe1f23772b37c1; Domain=.tiktok.com; Path=/; Secure; Expires=1778045004; tt_session_tlb_tag=sttt%7C5%7CreWf9xwMDlzA_h8jdys3wf________-ji4fpfjT0V1140MZnLSHWNBnXgRLIZvw1fxmxRRmvw7s%3D; Domain=.tiktok.com; Path=/; Secure; Expires=1778045004; sid_ucp_v1=1.0.0-KDYzMTBmY2U1ODFjN2FkYjNmOGUwYWE1YjcwYTk2N2FkYzhhMjMxMTEKIQiSiNvUwN_XhmkQzIS2yAYYswsgDDC1vrXIBjgIQBJIBBADGgJteSIgYWRlNTlmZjcxYzBjMGU1Y2MwZmUxZjIzNzcyYjM3YzE; Domain=.tiktok.com; Path=/; Secure; Expires=1778045004; ssid_ucp_v1=1.0.0-KDYzMTBmY2U1ODFjN2FkYjNmOGUwYWE1YjcwYTk2N2FkYzhhMjMxMTEKIQiSiNvUwN_XhmkQzIS2yAYYswsgDDC1vrXIBjgIQBJIBBADGgJteSIgYWRlNTlmZjcxYzBjMGU1Y2MwZmUxZjIzNzcyYjM3YzE; Domain=.tiktok.com; Path=/; Secure; Expires=1778045004; store-country-code=vn; Domain=.tiktok.com; Path=/; Expires=1794029034; store-country-code-src=uid; Domain=.tiktok.com; Path=/; Expires=1794029034; tt-target-idc=alisg; Domain=.tiktok.com; Path=/; Expires=1794029034; tt-target-idc-sign=X46gRkvSgmGWHXja-gzeN1KwdE4cBtH3zFXAhG3-BtWzH-YdFZEQct_uBwMTYtfjrNxqy_GJyyU9vrDSU9xBVMhZYzNMj8Yj-vL3ZdUiBlJfwT_RyqsMw9cBp-UMAurlaLw7iKPn1sOB_2Mr4OgfdC72r1rSon8aLN6RpZxfHlcPgzQDAzxGLO1WCcDi3Grn071JYzpIP3H4Uj5tKf5cHSGRn8O-z3hwE-QaTWdxP_Dv9m7mqKXg9LpTBaiRQ0apSWQMga4QK4y5B4To6e0pZD8oaixa2PVdqGeLesDSGOjsT94m5Qtsw2dBLvi1Cl2PDtg34s_m8F2kwZanwVGyMx5JeHbhEA1jVyuFTZ4wmF-6mQMCj4IoVYUBqf6cEHJl1nz6p3h7j4AFPdhgbDj7nwn0zI1o0xP8WGmE_kn9e53ehBx6IU-iOQJ-JXc_4e8_1n_tP7nZqBQAfB5B-a8mW0iUyH2XBzKKIebPZ8u02eRKDVUUZnutFcgBXjbQW4hW; Domain=.tiktok.com; Path=/; Expires=1794029034; ttwid=1%7CyHVVoWeMmc-3HMQzGeLAWTKsoEmn5lOxHLhrceV4g3w%7C1762493033%7Caa33d6157603beb187ae2fd554015cf463e69a9385fbc54d7a3e7a848a9df8fc; Domain=.tiktok.com; Path=/; Secure; Expires=1794029034; store-idc=alisg; Domain=.tiktok.com; Path=/; Expires=1794029034; store-country-sign=MEIEDGNAqWqR2a0er4zjeAQgMuurAVNuf3SOpc_lCsUS6OVOTEMJPGY7fje3VCShvuYEEKSUWUChT9xgz3oinfsoj_8; Domain=.tiktok.com; Path=/; Expires=1794029034; odin_tt=fdb338ea9924b66e069cd3826b52e91602d6c7c70440ed4a45253d1bdcb67e7b33079c363923c1afe01be7d6a0aed5f094b6d26ad61219129e2c4adf8ef71b17c80e515b61a158847d9b8a0bdf5ce20d; Domain=.tiktok.com; Path=/; Expires=1794029677; msToken=\"hx7BSPgRgPpecRzth56d-4VmoMwLX3y6d4CTS7XghO6T-s3uYyauu6s_q4fR0IXZe4yMTJWOmOjslVTkK-NEj_mMoww1_RiOAdVG_G6uzPyJMQiCzsXhIswbgY6slrxU-tenhjM2l9KyXpw=\"; Domain=.tiktok.com; Path=/; Secure; Expires=1766707277",
        "http_headers": {
          "User-Agent": "Mozilla/5.0",
          "Accept": "text/html,application/xhtml+xml,application/xml;q=0.9,*/*;q=0.8",
          "Accept-Language": "en-us,en;q=0.5",
          "Sec-Fetch-Mode": "navigate",
          "Referer": "https://www.tiktok.com/@shara.gym/video/7277616516865002784"
        },
        "format": "bytevc1_720p_428555-0 - 720x1280"
      },
      {
        "ext": "mp4",
        "vcodec": "h265",
        "acodec": "aac",
        "format_id": "bytevc1_720p_428555-1",
        "tbr": 428,
        "quality": 2,
        "preference": -1,
        "filesize": 577103,
        "width": 720,
        "height": 1280,
        "url": "https://v19-webapp-prime.tiktok.com/video/tos/useast2a/tos-useast2a-ve-0068c001-euttp/okRiaL2P4AiIMbnixaaJfflSfJ4AeHOn4GcehA/?a=1988&bti=ODszNWYuMDE6&ch=0&cr=3&dr=0&lr=all&cd=0%7C0%7C0%7C&cv=1&br=836&bt=418&cs=2&ds=3&ft=-Csk_m7nPD12NHcSZd-Ux_TvXY6e3wv251cAp&mime_type=video_mp4&qs=14&rc=cnF8b2hsc2d3SkBwaHIxaDFybndmN2lnOjg5ZWk6NzhkPDQ2OUBpanY4Njc6ZnVubTMzZjczM0BjRl5Nc3FePmJKYSNvYF90aHFmOiM1NGJgYGE0NmExMTZeXi5iYSNoai9fcjRvZXNgLS1kMWNzcw%3D%3D&btag=e000b0000&expire=1766016087&l=202512160801176868EDCD479534677EBE&ply_type=2&policy=2&signature=8f29aabc8d9bcf07c33254fd3ae44588&tk=tt_chain_token",
        "protocol": "https",
        "video_ext": "mp4",
        "audio_ext": "none",
        "resolution": "720x1280",
        "dynamic_range": "SDR",
        "aspect_ratio": 0.56,
        "cookies": "_ttp=34wyWDXvxmF602Htsl0oDR6JCNq; Domain=.tiktok.com; Path=/; Secure; Expires=1795834961; tt_csrf_token=A6kVUZcK-ro_L6C62WbmQwfALArHC4HF-pTM; Domain=.tiktok.com; Path=/; Secure; tt_chain_token=\"bIQCOyoJbQ000pox+IBxHQ==\"; Domain=.tiktok.com; Path=/; Secure; Expires=1781395277; passport_csrf_token=3e2175a5e77e24a26515b4e6f7b50740; Domain=.tiktok.com; Path=/; Secure; Expires=1767674732; passport_csrf_token_default=3e2175a5e77e24a26515b4e6f7b50740; Domain=.tiktok.com; Path=/; Secure; Expires=1767674732; s_v_web_id=verify_mhodh7s9_f6H7RhcI_zN3b_4VwP_AxSW_OnDGZUzFJBgu; Domain=.tiktok.com; Path=/; Secure; multi_sids=7569810985282094098%3Aade59ff71c0c0e5cc0fe1f23772b37c1; Domain=.tiktok.com; Path=/; Secure; Expires=1767677004; cmpl_token=AgQQAPOFF-RO0rkzsFuCpB0r82zGAoWNv4UOYKOhVw; Domain=.tiktok.com; Path=/; Secure; Expires=1767677004; sid_guard=ade59ff71c0c0e5cc0fe1f23772b37c1%7C1762493004%7C15552000%7CWed%2C+06-May-2026+05%3A23%3A24+GMT; Domain=.tiktok.com; Path=/; Secure; Expires=1793597004; uid_tt=ac0557b89a0248004ba199e09ced5e656aa70515a78deb5b62cd048a83d31edc; Domain=.tiktok.com; Path=/; Secure; Expires=1778045004; uid_tt_ss=ac0557b89a0248004ba199e09ced5e656aa70515a78deb5b62cd048a83d31edc; Domain=.tiktok.com; Path=/; Secure; Expires=1778045004; sid_tt=ade59ff71c0c0e5cc0fe1f23772b37c1; Domain=.tiktok.com; Path=/; Secure; Expires=1778045004; sessionid=ade59ff71c0c0e5cc0fe1f23772b37c1; Domain=.tiktok.com; Path=/; Secure; Expires=1778045004; sessionid_ss=ade59ff71c0c0e5cc0fe1f23772b37c1; Domain=.tiktok.com; Path=/; Secure; Expires=1778045004; tt_session_tlb_tag=sttt%7C5%7CreWf9xwMDlzA_h8jdys3wf________-ji4fpfjT0V1140MZnLSHWNBnXgRLIZvw1fxmxRRmvw7s%3D; Domain=.tiktok.com; Path=/; Secure; Expires=1778045004; sid_ucp_v1=1.0.0-KDYzMTBmY2U1ODFjN2FkYjNmOGUwYWE1YjcwYTk2N2FkYzhhMjMxMTEKIQiSiNvUwN_XhmkQzIS2yAYYswsgDDC1vrXIBjgIQBJIBBADGgJteSIgYWRlNTlmZjcxYzBjMGU1Y2MwZmUxZjIzNzcyYjM3YzE; Domain=.tiktok.com; Path=/; Secure; Expires=1778045004; ssid_ucp_v1=1.0.0-KDYzMTBmY2U1ODFjN2FkYjNmOGUwYWE1YjcwYTk2N2FkYzhhMjMxMTEKIQiSiNvUwN_XhmkQzIS2yAYYswsgDDC1vrXIBjgIQBJIBBADGgJteSIgYWRlNTlmZjcxYzBjMGU1Y2MwZmUxZjIzNzcyYjM3YzE; Domain=.tiktok.com; Path=/; Secure; Expires=1778045004; store-country-code=vn; Domain=.tiktok.com; Path=/; Expires=1794029034; store-country-code-src=uid; Domain=.tiktok.com; Path=/; Expires=1794029034; tt-target-idc=alisg; Domain=.tiktok.com; Path=/; Expires=1794029034; tt-target-idc-sign=X46gRkvSgmGWHXja-gzeN1KwdE4cBtH3zFXAhG3-BtWzH-YdFZEQct_uBwMTYtfjrNxqy_GJyyU9vrDSU9xBVMhZYzNMj8Yj-vL3ZdUiBlJfwT_RyqsMw9cBp-UMAurlaLw7iKPn1sOB_2Mr4OgfdC72r1rSon8aLN6RpZxfHlcPgzQDAzxGLO1WCcDi3Grn071JYzpIP3H4Uj5tKf5cHSGRn8O-z3hwE-QaTWdxP_Dv9m7mqKXg9LpTBaiRQ0apSWQMga4QK4y5B4To6e0pZD8oaixa2PVdqGeLesDSGOjsT94m5Qtsw2dBLvi1Cl2PDtg34s_m8F2kwZanwVGyMx5JeHbhEA1jVyuFTZ4wmF-6mQMCj4IoVYUBqf6cEHJl1nz6p3h7j4AFPdhgbDj7nwn0zI1o0xP8WGmE_kn9e53ehBx6IU-iOQJ-JXc_4e8_1n_tP7nZqBQAfB5B-a8mW0iUyH2XBzKKIebPZ8u02eRKDVUUZnutFcgBXjbQW4hW; Domain=.tiktok.com; Path=/; Expires=1794029034; ttwid=1%7CyHVVoWeMmc-3HMQzGeLAWTKsoEmn5lOxHLhrceV4g3w%7C1762493033%7Caa33d6157603beb187ae2fd554015cf463e69a9385fbc54d7a3e7a848a9df8fc; Domain=.tiktok.com; Path=/; Secure; Expires=1794029034; store-idc=alisg; Domain=.tiktok.com; Path=/; Expires=1794029034; store-country-sign=MEIEDGNAqWqR2a0er4zjeAQgMuurAVNuf3SOpc_lCsUS6OVOTEMJPGY7fje3VCShvuYEEKSUWUChT9xgz3oinfsoj_8; Domain=.tiktok.com; Path=/; Expires=1794029034; odin_tt=fdb338ea9924b66e069cd3826b52e91602d6c7c70440ed4a45253d1bdcb67e7b33079c363923c1afe01be7d6a0aed5f094b6d26ad61219129e2c4adf8ef71b17c80e515b61a158847d9b8a0bdf5ce20d; Domain=.tiktok.com; Path=/; Expires=1794029677; msToken=\"hx7BSPgRgPpecRzth56d-4VmoMwLX3y6d4CTS7XghO6T-s3uYyauu6s_q4fR0IXZe4yMTJWOmOjslVTkK-NEj_mMoww1_RiOAdVG_G6uzPyJMQiCzsXhIswbgY6slrxU-tenhjM2l9KyXpw=\"; Domain=.tiktok.com; Path=/; Secure; Expires=1766707277",
        "http_headers": {
          "User-Agent": "Mozilla/5.0",
          "Accept": "text/html,application/xhtml+xml,application/xml;q=0.9,*/*;q=0.8",
          "Accept-Language": "en-us,en;q=0.5",
          "Sec-Fetch-Mode": "navigate",
          "Referer": "https://www.tiktok.com/@shara.gym/video/7277616516865002784"
        },
        "format": "bytevc1_720p_428555-1 - 720x1280"
      },
      {
        "ext": "mp4",
        "vcodec": "h265",
        "acodec": "aac",
        "format_id": "bytevc1_1080p_578909-0",
        "tbr": 578,
        "quality": 3,
        "preference": -1,
        "filesize": 779574,
        "width": 1080,
        "height": 1920,
        "url": "https://v16-webapp-prime.tiktok.com/video/tos/useast2a/tos-useast2a-ve-0068c001-euttp/ogIGwiffZE0LfF224e5CI7TB1euAxLUt9PwkUf/?a=1988&bti=ODszNWYuMDE6&ch=0&cr=3&dr=0&lr=all&cd=0%7C0%7C0%7C&cv=1&br=1130&bt=565&cs=2&ds=4&ft=-Csk_m7nPD12NHcSZd-Ux_TvXY6e3wv251cAp&mime_type=video_mp4&qs=15&rc=NDk5ODM3ZDVmPDQ8OGZmOEBpanY4Njc6ZnVubTMzZjczM0A1YGIxMGM2Xl4xMjBgNl8xYSNoai9fcjRvZXNgLS1kMWNzcw%3D%3D&btag=e000b0000&expire=1766016087&l=202512160801176868EDCD479534677EBE&ply_type=2&policy=2&signature=f1e7553b25fe637dc8a19ff271b03fec&tk=tt_chain_token",
        "protocol": "https",
        "video_ext": "mp4",
        "audio_ext": "none",
        "resolution": "1080x1920",
        "dynamic_range": "SDR",
        "aspect_ratio": 0.56,
        "cookies": "_ttp=34wyWDXvxmF602Htsl0oDR6JCNq; Domain=.tiktok.com; Path=/; Secure; Expires=1795834961; tt_csrf_token=A6kVUZcK-ro_L6C62WbmQwfALArHC4HF-pTM; Domain=.tiktok.com; Path=/; Secure; tt_chain_token=\"bIQCOyoJbQ000pox+IBxHQ==\"; Domain=.tiktok.com; Path=/; Secure; Expires=1781395277; passport_csrf_token=3e2175a5e77e24a26515b4e6f7b50740; Domain=.tiktok.com; Path=/; Secure; Expires=1767674732; passport_csrf_token_default=3e2175a5e77e24a26515b4e6f7b50740; Domain=.tiktok.com; Path=/; Secure; Expires=1767674732; s_v_web_id=verify_mhodh7s9_f6H7RhcI_zN3b_4VwP_AxSW_OnDGZUzFJBgu; Domain=.tiktok.com; Path=/; Secure; multi_sids=7569810985282094098%3Aade59ff71c0c0e5cc0fe1f23772b37c1; Domain=.tiktok.com; Path=/; Secure; Expires=1767677004; cmpl_token=AgQQAPOFF-RO0rkzsFuCpB0r82zGAoWNv4UOYKOhVw; Domain=.tiktok.com; Path=/; Secure; Expires=1767677004; sid_guard=ade59ff71c0c0e5cc0fe1f23772b37c1%7C1762493004%7C15552000%7CWed%2C+06-May-2026+05%3A23%3A24+GMT; Domain=.tiktok.com; Path=/; Secure; Expires=1793597004; uid_tt=ac0557b89a0248004ba199e09ced5e656aa70515a78deb5b62cd048a83d31edc; Domain=.tiktok.com; Path=/; Secure; Expires=1778045004; uid_tt_ss=ac0557b89a0248004ba199e09ced5e656aa70515a78deb5b62cd048a83d31edc; Domain=.tiktok.com; Path=/; Secure; Expires=1778045004; sid_tt=ade59ff71c0c0e5cc0fe1f23772b37c1; Domain=.tiktok.com; Path=/; Secure; Expires=1778045004; sessionid=ade59ff71c0c0e5cc0fe1f23772b37c1; Domain=.tiktok.com; Path=/; Secure; Expires=1778045004; sessionid_ss=ade59ff71c0c0e5cc0fe1f23772b37c1; Domain=.tiktok.com; Path=/; Secure; Expires=1778045004; tt_session_tlb_tag=sttt%7C5%7CreWf9xwMDlzA_h8jdys3wf________-ji4fpfjT0V1140MZnLSHWNBnXgRLIZvw1fxmxRRmvw7s%3D; Domain=.tiktok.com; Path=/; Secure; Expires=1778045004; sid_ucp_v1=1.0.0-KDYzMTBmY2U1ODFjN2FkYjNmOGUwYWE1YjcwYTk2N2FkYzhhMjMxMTEKIQiSiNvUwN_XhmkQzIS2yAYYswsgDDC1vrXIBjgIQBJIBBADGgJteSIgYWRlNTlmZjcxYzBjMGU1Y2MwZmUxZjIzNzcyYjM3YzE; Domain=.tiktok.com; Path=/; Secure; Expires=1778045004; ssid_ucp_v1=1.0.0-KDYzMTBmY2U1ODFjN2FkYjNmOGUwYWE1YjcwYTk2N2FkYzhhMjMxMTEKIQiSiNvUwN_XhmkQzIS2yAYYswsgDDC1vrXIBjgIQBJIBBADGgJteSIgYWRlNTlmZjcxYzBjMGU1Y2MwZmUxZjIzNzcyYjM3YzE; Domain=.tiktok.com; Path=/; Secure; Expires=1778045004; store-country-code=vn; Domain=.tiktok.com; Path=/; Expires=1794029034; store-country-code-src=uid; Domain=.tiktok.com; Path=/; Expires=1794029034; tt-target-idc=alisg; Domain=.tiktok.com; Path=/; Expires=1794029034; tt-target-idc-sign=X46gRkvSgmGWHXja-gzeN1KwdE4cBtH3zFXAhG3-BtWzH-YdFZEQct_uBwMTYtfjrNxqy_GJyyU9vrDSU9xBVMhZYzNMj8Yj-vL3ZdUiBlJfwT_RyqsMw9cBp-UMAurlaLw7iKPn1sOB_2Mr4OgfdC72r1rSon8aLN6RpZxfHlcPgzQDAzxGLO1WCcDi3Grn071JYzpIP3H4Uj5tKf5cHSGRn8O-z3hwE-QaTWdxP_Dv9m7mqKXg9LpTBaiRQ0apSWQMga4QK4y5B4To6e0pZD8oaixa2PVdqGeLesDSGOjsT94m5Qtsw2dBLvi1Cl2PDtg34s_m8F2kwZanwVGyMx5JeHbhEA1jVyuFTZ4wmF-6mQMCj4IoVYUBqf6cEHJl1nz6p3h7j4AFPdhgbDj7nwn0zI1o0xP8WGmE_kn9e53ehBx6IU-iOQJ-JXc_4e8_1n_tP7nZqBQAfB5B-a8mW0iUyH2XBzKKIebPZ8u02eRKDVUUZnutFcgBXjbQW4hW; Domain=.tiktok.com; Path=/; Expires=1794029034; ttwid=1%7CyHVVoWeMmc-3HMQzGeLAWTKsoEmn5lOxHLhrceV4g3w%7C1762493033%7Caa33d6157603beb187ae2fd554015cf463e69a9385fbc54d7a3e7a848a9df8fc; Domain=.tiktok.com; Path=/; Secure; Expires=1794029034; store-idc=alisg; Domain=.tiktok.com; Path=/; Expires=1794029034; store-country-sign=MEIEDGNAqWqR2a0er4zjeAQgMuurAVNuf3SOpc_lCsUS6OVOTEMJPGY7fje3VCShvuYEEKSUWUChT9xgz3oinfsoj_8; Domain=.tiktok.com; Path=/; Expires=1794029034; odin_tt=fdb338ea9924b66e069cd3826b52e91602d6c7c70440ed4a45253d1bdcb67e7b33079c363923c1afe01be7d6a0aed5f094b6d26ad61219129e2c4adf8ef71b17c80e515b61a158847d9b8a0bdf5ce20d; Domain=.tiktok.com; Path=/; Expires=1794029677; msToken=\"hx7BSPgRgPpecRzth56d-4VmoMwLX3y6d4CTS7XghO6T-s3uYyauu6s_q4fR0IXZe4yMTJWOmOjslVTkK-NEj_mMoww1_RiOAdVG_G6uzPyJMQiCzsXhIswbgY6slrxU-tenhjM2l9KyXpw=\"; Domain=.tiktok.com; Path=/; Secure; Expires=1766707277",
        "http_headers": {
          "User-Agent": "Mozilla/5.0",
          "Accept": "text/html,application/xhtml+xml,application/xml;q=0.9,*/*;q=0.8",
          "Accept-Language": "en-us,en;q=0.5",
          "Sec-Fetch-Mode": "navigate",
          "Referer": "https://www.tiktok.com/@shara.gym/video/7277616516865002784"
        },
        "format": "bytevc1_1080p_578909-0 - 1080x1920"
      },
      {
        "ext": "mp4",
        "vcodec": "h265",
        "acodec": "aac",
        "format_id": "bytevc1_1080p_578909-1",
        "tbr": 578,
        "quality": 3,
        "preference": -1,
        "filesize": 779574,
        "width": 1080,
        "height": 1920,
        "url": "https://v19-webapp-prime.tiktok.com/video/tos/useast2a/tos-useast2a-ve-0068c001-euttp/ogIGwiffZE0LfF224e5CI7TB1euAxLUt9PwkUf/?a=1988&bti=ODszNWYuMDE6&ch=0&cr=3&dr=0&lr=all&cd=0%7C0%7C0%7C&cv=1&br=1130&bt=565&cs=2&ds=4&ft=-Csk_m7nPD12NHcSZd-Ux_TvXY6e3wv251cAp&mime_type=video_mp4&qs=15&rc=NDk5ODM3ZDVmPDQ8OGZmOEBpanY4Njc6ZnVubTMzZjczM0A1YGIxMGM2Xl4xMjBgNl8xYSNoai9fcjRvZXNgLS1kMWNzcw%3D%3D&btag=e000b0000&expire=1766016087&l=202512160801176868EDCD479534677EBE&ply_type=2&policy=2&signature=f1e7553b25fe637dc8a19ff271b03fec&tk=tt_chain_token",
        "protocol": "https",
        "video_ext": "mp4",
        "audio_ext": "none",
        "resolution": "1080x1920",
        "dynamic_range": "SDR",
        "aspect_ratio": 0.56,
        "cookies": "_ttp=34wyWDXvxmF602Htsl0oDR6JCNq; Domain=.tiktok.com; Path=/; Secure; Expires=1795834961; tt_csrf_token=A6kVUZcK-ro_L6C62WbmQwfALArHC4HF-pTM; Domain=.tiktok.com; Path=/; Secure; tt_chain_token=\"bIQCOyoJbQ000pox+IBxHQ==\"; Domain=.tiktok.com; Path=/; Secure; Expires=1781395277; passport_csrf_token=3e2175a5e77e24a26515b4e6f7b50740; Domain=.tiktok.com; Path=/; Secure; Expires=1767674732; passport_csrf_token_default=3e2175a5e77e24a26515b4e6f7b50740; Domain=.tiktok.com; Path=/; Secure; Expires=1767674732; s_v_web_id=verify_mhodh7s9_f6H7RhcI_zN3b_4VwP_AxSW_OnDGZUzFJBgu; Domain=.tiktok.com; Path=/; Secure; multi_sids=7569810985282094098%3Aade59ff71c0c0e5cc0fe1f23772b37c1; Domain=.tiktok.com; Path=/; Secure; Expires=1767677004; cmpl_token=AgQQAPOFF-RO0rkzsFuCpB0r82zGAoWNv4UOYKOhVw; Domain=.tiktok.com; Path=/; Secure; Expires=1767677004; sid_guard=ade59ff71c0c0e5cc0fe1f23772b37c1%7C1762493004%7C15552000%7CWed%2C+06-May-2026+05%3A23%3A24+GMT; Domain=.tiktok.com; Path=/; Secure; Expires=1793597004; uid_tt=ac0557b89a0248004ba199e09ced5e656aa70515a78deb5b62cd048a83d31edc; Domain=.tiktok.com; Path=/; Secure; Expires=1778045004; uid_tt_ss=ac0557b89a0248004ba199e09ced5e656aa70515a78deb5b62cd048a83d31edc; Domain=.tiktok.com; Path=/; Secure; Expires=1778045004; sid_tt=ade59ff71c0c0e5cc0fe1f23772b37c1; Domain=.tiktok.com; Path=/; Secure; Expires=1778045004; sessionid=ade59ff71c0c0e5cc0fe1f23772b37c1; Domain=.tiktok.com; Path=/; Secure; Expires=1778045004; sessionid_ss=ade59ff71c0c0e5cc0fe1f23772b37c1; Domain=.tiktok.com; Path=/; Secure; Expires=1778045004; tt_session_tlb_tag=sttt%7C5%7CreWf9xwMDlzA_h8jdys3wf________-ji4fpfjT0V1140MZnLSHWNBnXgRLIZvw1fxmxRRmvw7s%3D; Domain=.tiktok.com; Path=/; Secure; Expires=1778045004; sid_ucp_v1=1.0.0-KDYzMTBmY2U1ODFjN2FkYjNmOGUwYWE1YjcwYTk2N2FkYzhhMjMxMTEKIQiSiNvUwN_XhmkQzIS2yAYYswsgDDC1vrXIBjgIQBJIBBADGgJteSIgYWRlNTlmZjcxYzBjMGU1Y2MwZmUxZjIzNzcyYjM3YzE; Domain=.tiktok.com; Path=/; Secure; Expires=1778045004; ssid_ucp_v1=1.0.0-KDYzMTBmY2U1ODFjN2FkYjNmOGUwYWE1YjcwYTk2N2FkYzhhMjMxMTEKIQiSiNvUwN_XhmkQzIS2yAYYswsgDDC1vrXIBjgIQBJIBBADGgJteSIgYWRlNTlmZjcxYzBjMGU1Y2MwZmUxZjIzNzcyYjM3YzE; Domain=.tiktok.com; Path=/; Secure; Expires=1778045004; store-country-code=vn; Domain=.tiktok.com; Path=/; Expires=1794029034; store-country-code-src=uid; Domain=.tiktok.com; Path=/; Expires=1794029034; tt-target-idc=alisg; Domain=.tiktok.com; Path=/; Expires=1794029034; tt-target-idc-sign=X46gRkvSgmGWHXja-gzeN1KwdE4cBtH3zFXAhG3-BtWzH-YdFZEQct_uBwMTYtfjrNxqy_GJyyU9vrDSU9xBVMhZYzNMj8Yj-vL3ZdUiBlJfwT_RyqsMw9cBp-UMAurlaLw7iKPn1sOB_2Mr4OgfdC72r1rSon8aLN6RpZxfHlcPgzQDAzxGLO1WCcDi3Grn071JYzpIP3H4Uj5tKf5cHSGRn8O-z3hwE-QaTWdxP_Dv9m7mqKXg9LpTBaiRQ0apSWQMga4QK4y5B4To6e0pZD8oaixa2PVdqGeLesDSGOjsT94m5Qtsw2dBLvi1Cl2PDtg34s_m8F2kwZanwVGyMx5JeHbhEA1jVyuFTZ4wmF-6mQMCj4IoVYUBqf6cEHJl1nz6p3h7j4AFPdhgbDj7nwn0zI1o0xP8WGmE_kn9e53ehBx6IU-iOQJ-JXc_4e8_1n_tP7nZqBQAfB5B-a8mW0iUyH2XBzKKIebPZ8u02eRKDVUUZnutFcgBXjbQW4hW; Domain=.tiktok.com; Path=/; Expires=1794029034; ttwid=1%7CyHVVoWeMmc-3HMQzGeLAWTKsoEmn5lOxHLhrceV4g3w%7C1762493033%7Caa33d6157603beb187ae2fd554015cf463e69a9385fbc54d7a3e7a848a9df8fc; Domain=.tiktok.com; Path=/; Secure; Expires=1794029034; store-idc=alisg; Domain=.tiktok.com; Path=/; Expires=1794029034; store-country-sign=MEIEDGNAqWqR2a0er4zjeAQgMuurAVNuf3SOpc_lCsUS6OVOTEMJPGY7fje3VCShvuYEEKSUWUChT9xgz3oinfsoj_8; Domain=.tiktok.com; Path=/; Expires=1794029034; odin_tt=fdb338ea9924b66e069cd3826b52e91602d6c7c70440ed4a45253d1bdcb67e7b33079c363923c1afe01be7d6a0aed5f094b6d26ad61219129e2c4adf8ef71b17c80e515b61a158847d9b8a0bdf5ce20d; Domain=.tiktok.com; Path=/; Expires=1794029677; msToken=\"hx7BSPgRgPpecRzth56d-4VmoMwLX3y6d4CTS7XghO6T-s3uYyauu6s_q4fR0IXZe4yMTJWOmOjslVTkK-NEj_mMoww1_RiOAdVG_G6uzPyJMQiCzsXhIswbgY6slrxU-tenhjM2l9KyXpw=\"; Domain=.tiktok.com; Path=/; Secure; Expires=1766707277",
        "http_headers": {
          "User-Agent": "Mozilla/5.0",
          "Accept": "text/html,application/xhtml+xml,application/xml;q=0.9,*/*;q=0.8",
          "Accept-Language": "en-us,en;q=0.5",
          "Sec-Fetch-Mode": "navigate",
          "Referer": "https://www.tiktok.com/@shara.gym/video/7277616516865002784"
        },
        "format": "bytevc1_1080p_578909-1 - 1080x1920"
      }
    ],
    "subtitles": {},
    "http_headers": {
      "User-Agent": "Mozilla/5.0",
      "Accept": "text/html,application/xhtml+xml,application/xml;q=0.9,*/*;q=0.8",
      "Accept-Language": "en-us,en;q=0.5",
      "Sec-Fetch-Mode": "navigate",
      "Referer": "https://www.tiktok.com/@shara.gym/video/7277616516865002784"
    },
    "channel": "shara",
    "channel_id": "MS4wLjABAAAALcGEMZmp4gcO_PeMF3RpEeZMTQH6Y1JAOnJVJiQgVuu8M5j0GOTrwRF1Nsc-SVEd",
    "uploader": "shara.gym",
    "uploader_id": "7272924578375746593",
    "channel_url": "https://www.tiktok.com/@MS4wLjABAAAALcGEMZmp4gcO_PeMF3RpEeZMTQH6Y1JAOnJVJiQgVuu8M5j0GOTrwRF1Nsc-SVEd",
    "uploader_url": "https://www.tiktok.com/@shara.gym",
    "track": "All Eyes On Me - Instrumental",
    "album": "All Eyes On Me - Instrumental",
    "artists": [
      "Dj Belite"
    ],
    "duration": 10,
    "title": "Sexy secretary  #secretary #seductive #sexy #girl #body #viral #fyp #...",
    "description": "Sexy secretary  #secretary #seductive #sexy #girl #body #viral #fyp #foryou ",
    "timestamp": 1694452144,
    "view_count": 116500,
    "like_count": 657,
    "repost_count": 88,
    "comment_count": 58,
    "thumbnails": [
      {
        "id": "dynamicCover",
        "url": "https://p19-common-sign-useastred.tiktokcdn-eu.com/tos-useast2a-p-0037-euttp/994c69412ee0483384b3266d254db75d_1694452147~tplv-tiktokx-origin.image?dr=14575&x-expires=1766016000&x-signature=c6bib9CA6KnzxjNGzHBInNQlotE%3D&t=4d5b0474&ps=13740610&shp=81f88b70&shcp=43f4a2f9&idc=my",
        "preference": -2
      },
      {
        "id": "cover",
        "url": "https://p19-common-sign-useastred.tiktokcdn-eu.com/tos-useast2a-p-0037-euttp/ocfYgfnCgQJIev2jJebEjsvEaI56S0IiADGSBI~tplv-tiktokx-origin.image?dr=14575&x-expires=1766016000&x-signature=cRxUpBJoUvpE6i2yEJGOJPqbf14%3D&t=4d5b0474&ps=13740610&shp=81f88b70&shcp=43f4a2f9&idc=my",
        "preference": -1
      },
      {
        "id": "originCover",
        "url": "https://p19-common-sign-useastred.tiktokcdn-eu.com/tos-useast2a-p-0037-euttp/bb1ac4227db0448491c73700f72550f6_1694452146~tplv-tiktokx-origin.image?dr=14575&x-expires=1766016000&x-signature=rIwoZCay%2BiDMWRMv4Vrw%2F%2Fiwqgg%3D&t=4d5b0474&ps=13740610&shp=81f88b70&shcp=43f4a2f9&idc=my",
        "preference": -1
      }
    ],
    "webpage_url": "https://www.tiktok.com/@shara.gym/video/7277616516865002784",
    "webpage_url_basename": "7277616516865002784",
    "webpage_url_domain": "tiktok.com",
    "extractor": "TikTok",
    "extractor_key": "TikTok",
    "thumbnail": "https://p19-common-sign-useastred.tiktokcdn-eu.com/tos-useast2a-p-0037-euttp/bb1ac4227db0448491c73700f72550f6_1694452146~tplv-tiktokx-origin.image?dr=14575&x-expires=1766016000&x-signature=rIwoZCay%2BiDMWRMv4Vrw%2F%2Fiwqgg%3D&t=4d5b0474&ps=13740610&shp=81f88b70&shcp=43f4a2f9&idc=my",
    "display_id": "7277616516865002784",
    "fulltitle": "Sexy secretary  #secretary #seductive #sexy #girl #body #viral #fyp #...",
    "duration_string": "10",
    "upload_date": "20230911",
    "artist": "Dj Belite",
    "epoch": 1765843277,
    "ext": "mp4",
    "vcodec": "h265",
    "acodec": "aac",
    "format_id": "bytevc1_1080p_578909-1",
    "tbr": 578,
    "quality": 3,
    "preference": -1,
    "filesize": 779574,
    "width": 1080,
    "height": 1920,
    "url": "https://v19-webapp-prime.tiktok.com/video/tos/useast2a/tos-useast2a-ve-0068c001-euttp/ogIGwiffZE0LfF224e5CI7TB1euAxLUt9PwkUf/?a=1988&bti=ODszNWYuMDE6&ch=0&cr=3&dr=0&lr=all&cd=0%7C0%7C0%7C&cv=1&br=1130&bt=565&cs=2&ds=4&ft=-Csk_m7nPD12NHcSZd-Ux_TvXY6e3wv251cAp&mime_type=video_mp4&qs=15&rc=NDk5ODM3ZDVmPDQ8OGZmOEBpanY4Njc6ZnVubTMzZjczM0A1YGIxMGM2Xl4xMjBgNl8xYSNoai9fcjRvZXNgLS1kMWNzcw%3D%3D&btag=e000b0000&expire=1766016087&l=202512160801176868EDCD479534677EBE&ply_type=2&policy=2&signature=f1e7553b25fe637dc8a19ff271b03fec&tk=tt_chain_token",
    "protocol": "https",
    "video_ext": "mp4",
    "audio_ext": "none",
    "resolution": "1080x1920",
    "dynamic_range": "SDR",
    "aspect_ratio": 0.56,
    "cookies": "_ttp=34wyWDXvxmF602Htsl0oDR6JCNq; Domain=.tiktok.com; Path=/; Secure; Expires=1795834961; tt_csrf_token=A6kVUZcK-ro_L6C62WbmQwfALArHC4HF-pTM; Domain=.tiktok.com; Path=/; Secure; tt_chain_token=\"bIQCOyoJbQ000pox+IBxHQ==\"; Domain=.tiktok.com; Path=/; Secure; Expires=1781395277; passport_csrf_token=3e2175a5e77e24a26515b4e6f7b50740; Domain=.tiktok.com; Path=/; Secure; Expires=1767674732; passport_csrf_token_default=3e2175a5e77e24a26515b4e6f7b50740; Domain=.tiktok.com; Path=/; Secure; Expires=1767674732; s_v_web_id=verify_mhodh7s9_f6H7RhcI_zN3b_4VwP_AxSW_OnDGZUzFJBgu; Domain=.tiktok.com; Path=/; Secure; multi_sids=7569810985282094098%3Aade59ff71c0c0e5cc0fe1f23772b37c1; Domain=.tiktok.com; Path=/; Secure; Expires=1767677004; cmpl_token=AgQQAPOFF-RO0rkzsFuCpB0r82zGAoWNv4UOYKOhVw; Domain=.tiktok.com; Path=/; Secure; Expires=1767677004; sid_guard=ade59ff71c0c0e5cc0fe1f23772b37c1%7C1762493004%7C15552000%7CWed%2C+06-May-2026+05%3A23%3A24+GMT; Domain=.tiktok.com; Path=/; Secure; Expires=1793597004; uid_tt=ac0557b89a0248004ba199e09ced5e656aa70515a78deb5b62cd048a83d31edc; Domain=.tiktok.com; Path=/; Secure; Expires=1778045004; uid_tt_ss=ac0557b89a0248004ba199e09ced5e656aa70515a78deb5b62cd048a83d31edc; Domain=.tiktok.com; Path=/; Secure; Expires=1778045004; sid_tt=ade59ff71c0c0e5cc0fe1f23772b37c1; Domain=.tiktok.com; Path=/; Secure; Expires=1778045004; sessionid=ade59ff71c0c0e5cc0fe1f23772b37c1; Domain=.tiktok.com; Path=/; Secure; Expires=1778045004; sessionid_ss=ade59ff71c0c0e5cc0fe1f23772b37c1; Domain=.tiktok.com; Path=/; Secure; Expires=1778045004; tt_session_tlb_tag=sttt%7C5%7CreWf9xwMDlzA_h8jdys3wf________-ji4fpfjT0V1140MZnLSHWNBnXgRLIZvw1fxmxRRmvw7s%3D; Domain=.tiktok.com; Path=/; Secure; Expires=1778045004; sid_ucp_v1=1.0.0-KDYzMTBmY2U1ODFjN2FkYjNmOGUwYWE1YjcwYTk2N2FkYzhhMjMxMTEKIQiSiNvUwN_XhmkQzIS2yAYYswsgDDC1vrXIBjgIQBJIBBADGgJteSIgYWRlNTlmZjcxYzBjMGU1Y2MwZmUxZjIzNzcyYjM3YzE; Domain=.tiktok.com; Path=/; Secure; Expires=1778045004; ssid_ucp_v1=1.0.0-KDYzMTBmY2U1ODFjN2FkYjNmOGUwYWE1YjcwYTk2N2FkYzhhMjMxMTEKIQiSiNvUwN_XhmkQzIS2yAYYswsgDDC1vrXIBjgIQBJIBBADGgJteSIgYWRlNTlmZjcxYzBjMGU1Y2MwZmUxZjIzNzcyYjM3YzE; Domain=.tiktok.com; Path=/; Secure; Expires=1778045004; store-country-code=vn; Domain=.tiktok.com; Path=/; Expires=1794029034; store-country-code-src=uid; Domain=.tiktok.com; Path=/; Expires=1794029034; tt-target-idc=alisg; Domain=.tiktok.com; Path=/; Expires=1794029034; tt-target-idc-sign=X46gRkvSgmGWHXja-gzeN1KwdE4cBtH3zFXAhG3-BtWzH-YdFZEQct_uBwMTYtfjrNxqy_GJyyU9vrDSU9xBVMhZYzNMj8Yj-vL3ZdUiBlJfwT_RyqsMw9cBp-UMAurlaLw7iKPn1sOB_2Mr4OgfdC72r1rSon8aLN6RpZxfHlcPgzQDAzxGLO1WCcDi3Grn071JYzpIP3H4Uj5tKf5cHSGRn8O-z3hwE-QaTWdxP_Dv9m7mqKXg9LpTBaiRQ0apSWQMga4QK4y5B4To6e0pZD8oaixa2PVdqGeLesDSGOjsT94m5Qtsw2dBLvi1Cl2PDtg34s_m8F2kwZanwVGyMx5JeHbhEA1jVyuFTZ4wmF-6mQMCj4IoVYUBqf6cEHJl1nz6p3h7j4AFPdhgbDj7nwn0zI1o0xP8WGmE_kn9e53ehBx6IU-iOQJ-JXc_4e8_1n_tP7nZqBQAfB5B-a8mW0iUyH2XBzKKIebPZ8u02eRKDVUUZnutFcgBXjbQW4hW; Domain=.tiktok.com; Path=/; Expires=1794029034; ttwid=1%7CyHVVoWeMmc-3HMQzGeLAWTKsoEmn5lOxHLhrceV4g3w%7C1762493033%7Caa33d6157603beb187ae2fd554015cf463e69a9385fbc54d7a3e7a848a9df8fc; Domain=.tiktok.com; Path=/; Secure; Expires=1794029034; store-idc=alisg; Domain=.tiktok.com; Path=/; Expires=1794029034; store-country-sign=MEIEDGNAqWqR2a0er4zjeAQgMuurAVNuf3SOpc_lCsUS6OVOTEMJPGY7fje3VCShvuYEEKSUWUChT9xgz3oinfsoj_8; Domain=.tiktok.com; Path=/; Expires=1794029034; odin_tt=fdb338ea9924b66e069cd3826b52e91602d6c7c70440ed4a45253d1bdcb67e7b33079c363923c1afe01be7d6a0aed5f094b6d26ad61219129e2c4adf8ef71b17c80e515b61a158847d9b8a0bdf5ce20d; Domain=.tiktok.com; Path=/; Expires=1794029677; msToken=\"hx7BSPgRgPpecRzth56d-4VmoMwLX3y6d4CTS7XghO6T-s3uYyauu6s_q4fR0IXZe4yMTJWOmOjslVTkK-NEj_mMoww1_RiOAdVG_G6uzPyJMQiCzsXhIswbgY6slrxU-tenhjM2l9KyXpw=\"; Domain=.tiktok.com; Path=/; Secure; Expires=1766707277",
    "format": "bytevc1_1080p_578909-1 - 1080x1920",
    "_type": "video",
    "_version": {
      "version": "2025.12.08",
      "release_git_head": "7a52ff29d86efc8f3adeba977b2009ce40b8e52e",
      "repository": "yt-dlp/yt-dlp"
    }
  },
  "comments": [
    {
      "cid": "7583924206065681208",
      "text": "Crean",
      "author": "Ariel Jhony Meneses Mejia",
      "create_time": 1765769974,
      "like_count": 0,
      "reply_count": 0,
      "replies": []
    },
    {
      "cid": "7569783772939666198",
      "text": "Clean.",
      "author": "CottonCandyGirl",
      "create_time": 1762477705,
      "like_count": 0,
      "reply_count": 0,
      "replies": []
    },
    {
      "cid": "7569796684448826134",
      "text": "A piece to appreciate.",
      "author": "Lunar Light",
      "create_time": 1762480682,
      "like_count": 0,
      "reply_count": 0,
      "replies": []
    },
    {
      "cid": "7568359028590510870",
      "text": "Food for thought.",
      "author": "YourSweetPea",
      "create_time": 1762145942,
      "like_count": 0,
      "reply_count": 0,
      "replies": []
    },
    {
      "cid": "7322250086439912198",
      "text": "c🥰",
      "author": "O Pensador",
      "create_time": 1704844224,
      "like_count": 2,
      "reply_count": 0,
      "replies": []
    },
    {
      "cid": "7569121924556604182",
      "text": "You've built such a great community.",
      "author": "user2955608675926",
      "create_time": 1762323548,
      "like_count": 0,
      "reply_count": 0,
      "replies": []
    },
    {
      "cid": "7579593214550999864",
      "text": "Financial freedom📊✅ Philippines 🇵🇭",
      "author": "Amanda🦋",
      "create_time": 1764761577,
      "like_count": 0,
      "reply_count": 0,
      "replies": []
    },
    {
      "cid": "7568736327317308182",
      "text": "This is like visual ASMR.",
      "author": "user41281791719748",
      "create_time": 1762233799,
      "like_count": 0,
      "reply_count": 0,
      "replies": []
    },
    {
      "cid": "7567277568987431702",
      "text": "Snowy days.",
      "author": "qsx15",
      "create_time": 1761894128,
      "like_count": 0,
      "reply_count": 0,
      "replies": []
    },
    {
      "cid": "7569792820271121174",
      "text": "Awesome days.",
      "author": "StrawberryCloud",
      "create_time": 1762479817,
      "like_count": 0,
      "reply_count": 0,
      "replies": []
    },
    {
      "cid": "7569797538473263894",
      "text": "That guy. That girl.",
      "author": "YourSweetPea",
      "create_time": 1762480925,
      "like_count": 0,
      "reply_count": 0,
      "replies": []
    },
    {
      "cid": "7568742866858410754",
      "text": "The way it fits perfectly...",
      "author": "user75296140328612",
      "create_time": 1762235304,
      "like_count": 0,
      "reply_count": 0,
      "replies": []
    },
    {
      "cid": "7569791832672076566",
      "text": "Big effort.",
      "author": "YourSweetPea",
      "create_time": 1762479583,
      "like_count": 0,
      "reply_count": 0,
      "replies": []
    },
    {
      "cid": "7568727125572010774",
      "text": "Okay days.",
      "author": "PeachBlossom",
      "create_time": 1762231667,
      "like_count": 0,
      "reply_count": 0,
      "replies": []
    },
    {
      "cid": "7569798317841056534",
      "text": "A classic.",
      "author": "BubbleTeaAngel",
      "create_time": 1762481083,
      "like_count": 0,
      "reply_count": 0,
      "replies": []
    },
    {
      "cid": "7569794064679306006",
      "text": "An edge of days.",
      "author": "CottonCandyGirl",
      "create_time": 1762480099,
      "like_count": 0,
      "reply_count": 0,
      "replies": []
    },
    {
      "cid": "7568729171154993942",
      "text": "Preordained.",
      "author": "user2955608675926",
      "create_time": 1762232141,
      "like_count": 0,
      "reply_count": 0,
      "replies": []
    },
    {
      "cid": "7568732912666280726",
      "text": "Stunning days.",
      "author": "CottonCandyGirl",
      "create_time": 1762232993,
      "like_count": 0,
      "reply_count": 0,
      "replies": []
    },
    {
      "cid": "7568738218930848534",
      "text": "Unflinching.",
      "author": "HoneyBunnyBear",
      "create_time": 1762234230,
      "like_count": 0,
      "reply_count": 0,
      "replies": []
    },
    {
      "cid": "7569123650609496854",
      "text": "A living legend.",
      "author": "CottonCandyGirl",
      "create_time": 1762323962,
      "like_count": 0,
      "reply_count": 0,
      "replies": []
    },
    {
      "cid": "7569848562742543126",
      "text": "This is talent.",
      "author": "Bloom like a flower",
      "create_time": 1762492751,
      "like_count": 1,
      "reply_count": 0,
      "replies": []
    },
    {
      "cid": "7568358890200564502",
      "text": "Wonderful work.",
      "author": "PeachBlossom",
      "create_time": 1762145932,
      "like_count": 0,
      "reply_count": 0,
      "replies": []
    },
    {
      "cid": "7569781989130814230",
      "text": "The truth has been spoken.",
      "author": "BubbleTeaAngel",
      "create_time": 1762477279,
      "like_count": 0,
      "reply_count": 0,
      "replies": []
    },
    {
      "cid": "7568333190303384342",
      "text": "Not bad.",
      "author": "ZenithAura🌼",
      "create_time": 1762139989,
      "like_count": 0,
      "reply_count": 0,
      "replies": []
    },
    {
      "cid": "7569810172546368278",
      "text": "I get lost in your videos.",
      "author": "SparklePrincess",
      "create_time": 1762483843,
      "like_count": 0,
      "reply_count": 0,
      "replies": []
    },
    {
      "cid": "7569108905881338646",
      "text": "Take the W.",
      "author": "CottonCandyGirl",
      "create_time": 1762320534,
      "like_count": 0,
      "reply_count": 0,
      "replies": []
    },
    {
      "cid": "7568749777521853206",
      "text": "This is so imaginative.",
      "author": "user2083706235104",
      "create_time": 1762236902,
      "like_count": 0,
      "reply_count": 0,
      "replies": []
    },
    {
      "cid": "7569781821622240022",
      "text": "My spirit animal.",
      "author": "YourSweetPea",
      "create_time": 1762477216,
      "like_count": 0,
      "reply_count": 0,
      "replies": []
    },
    {
      "cid": "7574137033958933280",
      "text": "Va voir MYM, tape Muse_secrete",
      "author": "JJ",
      "create_time": 1763491211,
      "like_count": 0,
      "reply_count": 0,
      "replies": []
    },
    {
      "cid": "7568727087592555286",
      "text": "This is my go-to video.",
      "author": "PeachBlossom",
      "create_time": 1762231665,
      "like_count": 0,
      "reply_count": 0,
      "replies": []
    },
    {
      "cid": "7565259555883107094",
      "text": "😁",
      "author": "top_secretspeedy race",
      "create_time": 1761424263,
      "like_count": 1,
      "reply_count": 0,
      "replies": []
    },
    {
      "cid": "7564771590593250070",
      "text": "❤",
      "author": "Samseer_Art",
      "create_time": 1761310649,
      "like_count": 1,
      "reply_count": 0,
      "replies": []
    },
    {
      "cid": "7563410381495042838",
      "text": "✌",
      "author": "osman sik",
      "create_time": 1760993717,
      "like_count": 1,
      "reply_count": 0,
      "replies": []
    },
    {
      "cid": "7560370427311522582",
      "text": "🥰",
      "author": "Folgado Fernand",
      "create_time": 1760285922,
      "like_count": 1,
      "reply_count": 0,
      "replies": []
    },
    {
      "cid": "7582714040725209878",
      "text": "🤣🤣🤣",
      "author": "type0netraining",
      "create_time": 1765488203,
      "like_count": 0,
      "reply_count": 0,
      "replies": []
    },
    {
      "cid": "7581444894851351318",
      "text": "🥰",
      "author": "ZARCO5-HONDA-LCR.",
      "create_time": 1765192716,
      "like_count": 0,
      "reply_count": 0,
      "replies": []
    },
    {
      "cid": "7579091108866245398",
      "text": "🌹",
      "author": "Nicky Brammer",
      "create_time": 1764644738,
      "like_count": 0,
      "reply_count": 0,
      "replies": []
    },
    {
      "cid": "7579090975468880642",
      "text": "❤",
      "author": "Nicky Brammer",
      "create_time": 1764644738,
      "like_count": 0,
      "reply_count": 0,
      "replies": []
    },
    {
      "cid": "7579090995821658902",
      "text": "💗",
      "author": "Nicky Brammer",
      "create_time": 1764644738,
      "like_count": 0,
      "reply_count": 0,
      "replies": []
    },
    {
      "cid": "7578223756943672086",
      "text": "❤",
      "author": "Eros Garzotto",
      "create_time": 1764442725,
      "like_count": 0,
      "reply_count": 0,
      "replies": []
    },
    {
      "cid": "7576283041812087574",
      "text": "😁",
      "author": "jagtar19688gmail.com",
      "create_time": 1763990868,
      "like_count": 0,
      "reply_count": 0,
      "replies": []
    },
    {
      "cid": "7575861080692491030",
      "text": "👌",
      "author": "Kurt Ksrl",
      "create_time": 1763892625,
      "like_count": 0,
      "reply_count": 0,
      "replies": []
    },
    {
      "cid": "7573807004978529046",
      "text": "👍",
      "author": "Tigre Gaetano",
      "create_time": 1763414370,
      "like_count": 0,
      "reply_count": 0,
      "replies": []
    },
    {
      "cid": "7572935984633283335",
      "text": "💋",
      "author": "user2041807617804",
      "create_time": 1763211568,
      "like_count": 0,
      "reply_count": 0,
      "replies": []
    },
    {
      "cid": "7572671880307704594",
      "text": "🥰",
      "author": "Dave  Gee",
      "create_time": 1763150093,
      "like_count": 0,
      "reply_count": 0,
      "replies": []
    },
    {
      "cid": "7568523370044850955",
      "text": "♥",
      "author": "Alisher",
      "create_time": 1762184178,
      "like_count": 0,
      "reply_count": 0,
      "replies": []
    },
    {
      "cid": "7566740045169623830",
      "text": "👍👍👍",
      "author": "Tatul Hambardzumyan",
      "create_time": 1761768963,
      "like_count": 0,
      "reply_count": 0,
      "replies": []
    },
    {
      "cid": "7566383704585470722",
      "text": "🌹🌹🌹",
      "author": "Beko",
      "create_time": 1761686000,
      "like_count": 0,
      "reply_count": 0,
      "replies": []
    },
    {
      "cid": "7565596462944912160",
      "text": "👍",
      "author": "Paulo Pinto Ferreira",
      "create_time": 1761502701,
      "like_count": 0,
      "reply_count": 0,
      "replies": []
    },
    {
      "cid": "7564193945853805328",
      "text": "😂",
      "author": "Lobo Alfa",
      "create_time": 1761176166,
      "like_count": 0,
      "reply_count": 0,
      "replies": []
    },
    {
      "cid": "7562349069231194902",
      "text": "🥰",
      "author": "James Osborne",
      "create_time": 1760746645,
      "like_count": 0,
      "reply_count": 0,
      "replies": []
    },
    {
      "cid": "7567293154044265238",
      "text": "I could watch this all day.",
      "author": "EtherealVibe",
      "create_time": 1761897755,
      "like_count": 0,
      "reply_count": 0,
      "replies": []
    },
    {
      "cid": "7563777715226379030",
      "text": "💋",
      "author": "chickenitza",
      "create_time": 1761079248,
      "like_count": 0,
      "reply_count": 0,
      "replies": []
    },
    {
      "cid": "7569815480484004630",
      "text": "Evolution to witness.",
      "author": "SparklePrincess",
      "create_time": 1762485069,
      "like_count": 0,
      "reply_count": 0,
      "replies": []
    },
    {
      "cid": "7569795402329817878",
      "text": "You are the bar.",
      "author": "YourSweetPea",
      "create_time": 1762480385,
      "like_count": 0,
      "reply_count": 0,
      "replies": []
    },
    {
      "cid": "7568727151210890006",
      "text": "A flaw of days.",
      "author": "CottonCandyGirl",
      "create_time": 1762231658,
      "like_count": 0,
      "reply_count": 0,
      "replies": []
    },
    {
      "cid": "7568359127610016534",
      "text": "HIM. HER. THEM.",
      "author": "PeachBlossom",
      "create_time": 1762145969,
      "like_count": 0,
      "reply_count": 0,
      "replies": []
    },
    {
      "cid": "7568359025239573270",
      "text": "A genius.",
      "author": "PeachBlossom",
      "create_time": 1762145942,
      "like_count": 0,
      "reply_count": 0,
      "replies": []
    }
  ]
}